rtl/router_iact.v
`timescale 1ns / 1ps

module router_iact #( parameter DATA_BITWIDTH = 16,
		      parameter ADDR_BITWIDTH_GLB = 10,
		      parameter ADDR_BITWIDTH_SPAD = 9,
						
		      parameter X_dim = 5,
                      parameter Y_dim = 3,
                      parameter kernel_size = 3,
                      parameter act_size = 5,
						
		      parameter A_READ_ADDR =100, 
                      parameter A_LOAD_ADDR = 0
		     )
					
		     (	
		      input clk,
		      input reset,
						
		      //for reading glb
		      input [DATA_BITWIDTH-1 : 0] r_data_glb_iact,
		      output reg [ADDR_BITWIDTH_GLB-1 : 0] r_addr_glb_iact,
		      output reg read_req_glb_iact,
						
		      //for writing to spad
		      output reg [DATA_BITWIDTH-1 : 0] w_data_spad,
		      output reg load_en_spad,
						
		      //Input from control unit to load weights to spad
		      input load_spad_ctrl
			
		     );
				
					
	// enum reg [2:0] {IDLE=3'b000, READ_GLB=3'b001, WRITE_SPAD=3'b010, READ_GLB_0=3'b011} state;
	reg [2:0] state;		
	localparam IDLE=3'b000;
	localparam READ_GLB=3'b001;
	localparam WRITE_SPAD=3'b010;
	localparam READ_GLB_0=3'b011;
	reg [5:0] filt_count;
		
	always@(posedge clk) begin
		// $display("State: %s,filt_count: %d", state.name(),filt_count);
		if(reset) begin
			read_req_glb_iact <= 0;
			r_addr_glb_iact <= 0;
			load_en_spad <= 0;
			filt_count <= 0;
			state <= IDLE;
		end else begin
			case(state)
				IDLE:begin
				     if(load_spad_ctrl) begin
					read_req_glb_iact <= 1;
					r_addr_glb_iact <= A_READ_ADDR;
					load_en_spad <= 0;
					state <= READ_GLB;
				     end else begin
					read_req_glb_iact <= 0;
					load_en_spad <= 0;
					state <= IDLE;
				     end
				     end
					
				READ_GLB:begin
						
					 filt_count <= filt_count + 1;
					 r_addr_glb_iact <= r_addr_glb_iact + 1;
					 w_data_spad <= r_data_glb_iact;
					 state <= WRITE_SPAD;
					 end
					
				WRITE_SPAD:begin
					   load_en_spad <= 1;
					   if(filt_count == (act_size**2)) begin
						w_data_spad <= r_data_glb_iact;
						filt_count <= 0;
						r_addr_glb_iact <= A_READ_ADDR;
							
						state <= IDLE;
					   end else begin
						w_data_spad <= r_data_glb_iact;
						filt_count <= filt_count + 1;
						r_addr_glb_iact <= r_addr_glb_iact + 1;
						state <= WRITE_SPAD;
					   end
					   end
			endcase
		end
	end
 
endmodule

rtl/router_iact_generic.v
`timescale 1ns / 1ps

module router_generic_iact
#(
    parameter DATA_BITWIDTH      = 16,
    parameter ADDR_BITWIDTH_GLB  = 10,
    parameter ADDR_BITWIDTH_SPAD = 9,

    parameter X_dim       = 5,
    parameter Y_dim       = 3,
    parameter kernel_size = 3,
    parameter act_size    = 5,

    parameter A_READ_ADDR = 100,
    parameter A_LOAD_ADDR = 0,

    // 0=NORTH, 1=SOUTH, 2=WEST, 3=EAST
    parameter integer COMPUTE_DIR = 2
)
(
    input clk,
    input reset,
    input [3:0] router_mode,

    // GLB interface
    output [ADDR_BITWIDTH_GLB-1:0] glb_addr_read,
    output                         glb_req_read,

    // Inputs
    input [DATA_BITWIDTH-1:0] north_data_i,
    input                      north_enable_i,
    input [DATA_BITWIDTH-1:0] south_data_i,
    input                      south_enable_i,
    input [DATA_BITWIDTH-1:0] west_data_i,
    input                      west_enable_i,
    input [DATA_BITWIDTH-1:0] east_data_i,
    input                      east_enable_i,

    // Outputs
    output reg [DATA_BITWIDTH-1:0] north_data_o,
    output reg                     north_enable_o,
    output reg [DATA_BITWIDTH-1:0] south_data_o,
    output reg                     south_enable_o,
    output reg [DATA_BITWIDTH-1:0] west_data_o,
    output reg                     west_enable_o,
    output reg [DATA_BITWIDTH-1:0] east_data_o,
    output reg                     east_enable_o
);

    // --------------------------------------------------
    // 1. Arbitration (IDENTICAL to west router)
    // north > south > west > east
    // --------------------------------------------------
    reg [DATA_BITWIDTH-1:0] data_out;
    reg load_spad_ctrl_c;

    always @(*) begin
        if (north_enable_i) begin
            data_out = north_data_i;
            load_spad_ctrl_c = 1'b1;
        end else if (south_enable_i) begin
            data_out = south_data_i;
            load_spad_ctrl_c = 1'b1;
        end else if (west_enable_i) begin
            data_out = west_data_i;
            load_spad_ctrl_c = 1'b1;
        end else if (east_enable_i) begin
            data_out = east_data_i;
            load_spad_ctrl_c = 1'b1;
        end else begin
            data_out = {DATA_BITWIDTH{1'b0}};
            load_spad_ctrl_c = 1'b0;
        end
    end

    // --------------------------------------------------
    // 2. Edge-detected load pulse (EXACT match)
    // --------------------------------------------------
    reg load_ff0, load_ff1;
    wire load_spad_ctrl;

    assign load_spad_ctrl = load_ff0 & ~load_ff1;

    always @(posedge clk) begin
        if (reset) begin
            load_ff0 <= 1'b0;
            load_ff1 <= 1'b0;
        end else begin
            load_ff0 <= load_spad_ctrl_c;
            load_ff1 <= load_ff0;
        end
    end

    // --------------------------------------------------
    // 3. router_iact (UNCHANGED)
    // --------------------------------------------------
    wire [DATA_BITWIDTH-1:0] spad_data;
    wire                     spad_en;

    router_iact #(
        .DATA_BITWIDTH(DATA_BITWIDTH),
        .ADDR_BITWIDTH_GLB(ADDR_BITWIDTH_GLB),
        .ADDR_BITWIDTH_SPAD(ADDR_BITWIDTH_SPAD),
        .X_dim(X_dim),
        .Y_dim(Y_dim),
        .kernel_size(kernel_size),
        .act_size(act_size),
        .A_READ_ADDR(A_READ_ADDR),
        .A_LOAD_ADDR(A_LOAD_ADDR)
    ) router_iact_0 (
        .clk(clk),
        .reset(reset),
        .r_data_glb_iact(data_out),
        .r_addr_glb_iact(glb_addr_read),
        .read_req_glb_iact(glb_req_read),
        .w_data_spad(spad_data),
        .load_en_spad(spad_en),
        .load_spad_ctrl(load_spad_ctrl)
    );

    // --------------------------------------------------
    // 4. Routing logic (PURE, SPAD-INDEPENDENT)
    // --------------------------------------------------
    localparam ALL        = 0,
               NORTH      = 1,
               SOUTH      = 2,
               WEST       = 3,
               EAST       = 4,
               EASTNORTH  = 5,
               EASTSOUTH  = 6,
               EASTWEST   = 7,
               WESTNORTH  = 8,
               WESTSOUTH  = 9,
               WESTEAST   = 10,
               CLOSED     = 11;

    always @(*) begin
        // defaults
        north_data_o = 0; north_enable_o = 0;
        south_data_o = 0; south_enable_o = 0;
        west_data_o  = 0; west_enable_o  = 0;
        east_data_o  = 0; east_enable_o  = 0;

        if (router_mode != CLOSED) begin
            case (router_mode)
                ALL: begin
                    north_data_o = data_out; north_enable_o = 1;
                    south_data_o = data_out; south_enable_o = 1;
                    east_data_o  = data_out; east_enable_o  = 1;
                end
                NORTH: begin north_data_o = data_out; north_enable_o = 1; end
                SOUTH: begin south_data_o = data_out; south_enable_o = 1; end
                EAST:  begin east_data_o  = data_out; east_enable_o  = 1; end
                EASTNORTH: begin
                    east_data_o  = data_out; east_enable_o  = 1;
                    north_data_o = data_out; north_enable_o = 1;
                end
                EASTSOUTH: begin
                    east_data_o  = data_out; east_enable_o  = 1;
                    south_data_o = data_out; south_enable_o = 1;
                end
                WESTNORTH: begin
                    west_data_o  = data_out; west_enable_o  = 1;
                    north_data_o = data_out; north_enable_o = 1;
                end
                WESTSOUTH: begin
                    west_data_o  = data_out; west_enable_o  = 1;
                    south_data_o = data_out; south_enable_o = 1;
                end
                WESTEAST: begin
                    west_data_o  = data_out; west_enable_o  = 1;
                    east_data_o  = data_out; east_enable_o  = 1;
                end
            endcase
        end
    end

    // --------------------------------------------------
    // 5. SPAD → COMPUTE direction (STRUCTURAL, SEPARATE)
    // --------------------------------------------------
    generate
        if (COMPUTE_DIR == 0) begin
            always @(*) begin
                north_data_o   = spad_data;
                north_enable_o = spad_en;
            end
        end else if (COMPUTE_DIR == 1) begin
            always @(*) begin
                south_data_o   = spad_data;
                south_enable_o = spad_en;
            end
        end else if (COMPUTE_DIR == 2) begin
            always @(*) begin
                west_data_o    = spad_data;
                west_enable_o  = spad_en;
            end
        end else if (COMPUTE_DIR == 3) begin
            always @(*) begin
                east_data_o    = spad_data;
                east_enable_o  = spad_en;
            end
        end
    endgenerate

endmodule

testbench/router_iact_tb.v
`timescale 1ns/1ps

module tb_router_generic_iact;

    // -------------------------------------------------
    // Parameters
    // -------------------------------------------------
    localparam DATA_BITWIDTH     = 16;
    localparam ADDR_BITWIDTH_GLB = 10;

    // -------------------------------------------------
    // DUT signals
    // -------------------------------------------------
    reg clk;
    reg reset;
    reg [3:0] router_mode;

    wire [ADDR_BITWIDTH_GLB-1:0] glb_addr_read;
    wire                         glb_req_read;

    reg  [DATA_BITWIDTH-1:0] north_data_i;
    reg                       north_enable_i;
    reg  [DATA_BITWIDTH-1:0] south_data_i;
    reg                       south_enable_i;
    reg  [DATA_BITWIDTH-1:0] west_data_i;
    reg                       west_enable_i;
    reg  [DATA_BITWIDTH-1:0] east_data_i;
    reg                       east_enable_i;

    wire [DATA_BITWIDTH-1:0] north_data_o;
    wire                     north_enable_o;
    wire [DATA_BITWIDTH-1:0] south_data_o;
    wire                     south_enable_o;
    wire [DATA_BITWIDTH-1:0] west_data_o;
    wire                     west_enable_o;
    wire [DATA_BITWIDTH-1:0] east_data_o;
    wire                     east_enable_o;

    // -------------------------------------------------
    // DUT instance
    // COMPUTE_DIR = WEST (drop-in match)
    // -------------------------------------------------
    router_generic_iact #(
        .DATA_BITWIDTH(DATA_BITWIDTH),
        .ADDR_BITWIDTH_GLB(ADDR_BITWIDTH_GLB),
        .COMPUTE_DIR(2) // WEST
    ) dut (
        .clk(clk),
        .reset(reset),
        .router_mode(router_mode),

        .glb_addr_read(glb_addr_read),
        .glb_req_read(glb_req_read),

        .north_data_i(north_data_i),
        .north_enable_i(north_enable_i),
        .south_data_i(south_data_i),
        .south_enable_i(south_enable_i),
        .west_data_i(west_data_i),
        .west_enable_i(west_enable_i),
        .east_data_i(east_data_i),
        .east_enable_i(east_enable_i),

        .north_data_o(north_data_o),
        .north_enable_o(north_enable_o),
        .south_data_o(south_data_o),
        .south_enable_o(south_enable_o),
        .west_data_o(west_data_o),
        .west_enable_o(west_enable_o),
        .east_data_o(east_data_o),
        .east_enable_o(east_enable_o)
    );

    // -------------------------------------------------
    // Clock (100 MHz)
    // -------------------------------------------------
    always #5 clk = ~clk;

    // -------------------------------------------------
    // VCD
    // -------------------------------------------------
    initial begin
        $dumpfile("router_generic_iact_tb.vcd");
        $dumpvars(0, tb_router_generic_iact);
    end

    // -------------------------------------------------
    // Helpers
    // -------------------------------------------------
    task clear_inputs;
        begin
            north_enable_i = 0;
            south_enable_i = 0;
            west_enable_i  = 0;
            east_enable_i  = 0;
            north_data_i   = 0;
            south_data_i   = 0;
            west_data_i    = 0;
            east_data_i    = 0;
        end
    endtask

    task wait_clk(input integer n);
        integer i;
        begin
            for (i = 0; i < n; i = i + 1)
                @(posedge clk);
        end
    endtask

    // -------------------------------------------------
    // Test sequence
    // -------------------------------------------------
    initial begin
        clk = 0;
        reset = 1;
        router_mode = 0;
        clear_inputs();

        // -------- Reset --------
        wait_clk(3);
        reset = 0;
        wait_clk(2);

        // =================================================
        // TEST 1: Routing ONLY (no SPAD activity)
        // =================================================
        router_mode = 2; // SOUTH
        north_data_i   = 16'hAAAA;
        north_enable_i = 1;

        wait_clk(2);
        clear_inputs();

        // =================================================
        // TEST 2: CLOSED mode blocks routing
        // =================================================
        router_mode = 11; // CLOSED
        north_data_i   = 16'hBBBB;
        north_enable_i = 1;

        wait_clk(2);
        clear_inputs();

        // =================================================
        // TEST 3: SPAD load (isolated)
        // Routing must NOT toggle
        // =================================================
        router_mode = 11; // CLOSED

        west_data_i   = 16'h0101;
        west_enable_i = 1;   // triggers SPAD load

        wait_clk(1);
        west_enable_i = 0;

        // Observe SPAD writes
        wait_clk(10);

        // =================================================
        // TEST 4: Routing + SPAD overlap
        // =================================================
        router_mode = 4; // EAST
        north_data_i   = 16'hCCCC;
        north_enable_i = 1;

        wait_clk(1);
        north_enable_i = 0;

        // Trigger SPAD load again
        west_data_i   = 16'h0202;
        west_enable_i = 1;
        wait_clk(1);
        west_enable_i = 0;

        wait_clk(10);

        // =================================================
        // END
        // =================================================
        wait_clk(5);
        $finish;
    end

endmodule

router_generic_iact_tb.vcd
$date
	Sun Dec 14 18:40:26 2025
$end
$version
	Icarus Verilog
$end
$timescale
	1ps
$end
$scope module tb_router_generic_iact $end
$var wire 1 ! west_enable_o $end
$var wire 16 " west_data_o [15:0] $end
$var wire 1 # south_enable_o $end
$var wire 16 $ south_data_o [15:0] $end
$var wire 1 % north_enable_o $end
$var wire 16 & north_data_o [15:0] $end
$var wire 1 ' glb_req_read $end
$var wire 10 ( glb_addr_read [9:0] $end
$var wire 1 ) east_enable_o $end
$var wire 16 * east_data_o [15:0] $end
$var parameter 32 + ADDR_BITWIDTH_GLB $end
$var parameter 32 , DATA_BITWIDTH $end
$var reg 1 - clk $end
$var reg 16 . east_data_i [15:0] $end
$var reg 1 / east_enable_i $end
$var reg 16 0 north_data_i [15:0] $end
$var reg 1 1 north_enable_i $end
$var reg 1 2 reset $end
$var reg 4 3 router_mode [3:0] $end
$var reg 16 4 south_data_i [15:0] $end
$var reg 1 5 south_enable_i $end
$var reg 16 6 west_data_i [15:0] $end
$var reg 1 7 west_enable_i $end
$scope module dut $end
$var wire 1 - clk $end
$var wire 16 8 east_data_i [15:0] $end
$var wire 1 / east_enable_i $end
$var wire 1 9 load_spad_ctrl $end
$var wire 16 : north_data_i [15:0] $end
$var wire 1 1 north_enable_i $end
$var wire 1 2 reset $end
$var wire 4 ; router_mode [3:0] $end
$var wire 16 < south_data_i [15:0] $end
$var wire 1 5 south_enable_i $end
$var wire 16 = west_data_i [15:0] $end
$var wire 1 7 west_enable_i $end
$var wire 1 > spad_en $end
$var wire 16 ? spad_data [15:0] $end
$var wire 1 ' glb_req_read $end
$var wire 10 @ glb_addr_read [9:0] $end
$var parameter 32 A ADDR_BITWIDTH_GLB $end
$var parameter 32 B ADDR_BITWIDTH_SPAD $end
$var parameter 32 C ALL $end
$var parameter 32 D A_LOAD_ADDR $end
$var parameter 32 E A_READ_ADDR $end
$var parameter 32 F CLOSED $end
$var parameter 32 G COMPUTE_DIR $end
$var parameter 32 H DATA_BITWIDTH $end
$var parameter 32 I EAST $end
$var parameter 32 J EASTNORTH $end
$var parameter 32 K EASTSOUTH $end
$var parameter 32 L EASTWEST $end
$var parameter 32 M NORTH $end
$var parameter 32 N SOUTH $end
$var parameter 32 O WEST $end
$var parameter 32 P WESTEAST $end
$var parameter 32 Q WESTNORTH $end
$var parameter 32 R WESTSOUTH $end
$var parameter 32 S X_dim $end
$var parameter 32 T Y_dim $end
$var parameter 32 U act_size $end
$var parameter 32 V kernel_size $end
$var reg 16 W data_out [15:0] $end
$var reg 16 X east_data_o [15:0] $end
$var reg 1 ) east_enable_o $end
$var reg 1 Y load_ff0 $end
$var reg 1 Z load_ff1 $end
$var reg 1 [ load_spad_ctrl_c $end
$var reg 16 \ north_data_o [15:0] $end
$var reg 1 % north_enable_o $end
$var reg 16 ] south_data_o [15:0] $end
$var reg 1 # south_enable_o $end
$var reg 16 ^ west_data_o [15:0] $end
$var reg 1 ! west_enable_o $end
$scope begin genblk1 $end
$upscope $end
$scope module router_iact_0 $end
$var wire 1 - clk $end
$var wire 1 9 load_spad_ctrl $end
$var wire 16 _ r_data_glb_iact [15:0] $end
$var wire 1 2 reset $end
$var parameter 32 ` ADDR_BITWIDTH_GLB $end
$var parameter 32 a ADDR_BITWIDTH_SPAD $end
$var parameter 32 b A_LOAD_ADDR $end
$var parameter 32 c A_READ_ADDR $end
$var parameter 32 d DATA_BITWIDTH $end
$var parameter 3 e IDLE $end
$var parameter 3 f READ_GLB $end
$var parameter 3 g READ_GLB_0 $end
$var parameter 3 h WRITE_SPAD $end
$var parameter 32 i X_dim $end
$var parameter 32 j Y_dim $end
$var parameter 32 k act_size $end
$var parameter 32 l kernel_size $end
$var reg 6 m filt_count [5:0] $end
$var reg 1 > load_en_spad $end
$var reg 10 n r_addr_glb_iact [9:0] $end
$var reg 1 ' read_req_glb_iact $end
$var reg 3 o state [2:0] $end
$var reg 16 p w_data_spad [15:0] $end
$upscope $end
$upscope $end
$scope task clear_inputs $end
$upscope $end
$scope task wait_clk $end
$var integer 32 q i [31:0] $end
$var integer 32 r n [31:0] $end
$upscope $end
$upscope $end
$enddefinitions $end
$comment Show the parameter values. $end
$dumpall
b11 l
b101 k
b11 j
b101 i
b10 h
b11 g
b1 f
b0 e
b10000 d
b1100100 c
b0 b
b1001 a
b1010 `
b11 V
b101 U
b11 T
b101 S
b1001 R
b1000 Q
b1010 P
b11 O
b10 N
b1 M
b111 L
b110 K
b101 J
b100 I
b10000 H
b10 G
b1011 F
b1100100 E
b0 D
b0 C
b1001 B
b1010 A
b10000 ,
b1010 +
$end
#0
$dumpvars
b11 r
b0 q
bx p
bx o
bx n
bx m
b0 _
b0 ^
b0 ]
b0 \
0[
xZ
xY
b0 X
b0 W
bx @
bx ?
x>
b0 =
b0 <
b0 ;
b0 :
x9
b0 8
07
b0 6
05
b0 4
b0 3
12
01
b0 0
0/
b0 .
0-
b0 *
1)
bx (
x'
b0 &
1%
b0 $
1#
b0 "
0!
$end
#5000
bx "
bx ^
09
b0 o
b0 m
0>
b0 (
b0 @
b0 n
0'
0Z
0Y
b1 q
1-
#10000
0-
#15000
b10 q
1-
#20000
0-
#25000
b10 r
02
b0 q
1-
#30000
0-
#35000
b1 q
1-
#40000
0-
#45000
b1010101010101010 $
b1010101010101010 ]
1[
b1010101010101010 W
b1010101010101010 _
0)
b0 "
b0 ^
1#
0%
11
b1010101010101010 0
b1010101010101010 :
b10 3
b10 ;
b0 q
1-
#50000
0-
#55000
19
1Y
b1 q
1-
#60000
0-
#65000
09
b1 o
b1100100 (
b1100100 @
b1100100 n
1'
1Z
0#
b0 $
b0 ]
b1011101110111011 W
b1011101110111011 _
b1011 3
b1011 ;
b1011101110111011 0
b1011101110111011 :
11
b0 q
1-
#70000
0-
#75000
b1011101110111011 "
b1011101110111011 ^
b10 o
b1011101110111011 ?
b1011101110111011 p
b1100101 (
b1100101 @
b1100101 n
b1 m
b1 q
1-
#80000
0-
#85000
1!
b1100110 (
b1100110 @
b1100110 n
b10 m
1>
b1011101110111011 "
b1011101110111011 ^
b100000001 W
b100000001 _
b1 r
17
b100000001 6
b100000001 =
b0 0
b0 :
01
b0 q
1-
#90000
0-
#95000
b1100111 (
b1100111 @
b1100111 n
b11 m
b100000001 ?
b100000001 p
1!
b100000001 "
b100000001 ^
0[
b0 W
b0 _
b1010 r
07
b0 q
1-
#100000
0-
#105000
b0 "
b0 ^
b1101000 (
b1101000 @
b1101000 n
b100 m
b0 ?
b0 p
0Y
b1 q
1-
#110000
0-
#115000
0Z
b1101001 (
b1101001 @
b1101001 n
b101 m
b10 q
1-
#120000
0-
#125000
b1101010 (
b1101010 @
b1101010 n
b110 m
b11 q
1-
#130000
0-
#135000
b1101011 (
b1101011 @
b1101011 n
b111 m
b100 q
1-
#140000
0-
#145000
b1101100 (
b1101100 @
b1101100 n
b1000 m
b101 q
1-
#150000
0-
#155000
b1101101 (
b1101101 @
b1101101 n
b1001 m
b110 q
1-
#160000
0-
#165000
b1101110 (
b1101110 @
b1101110 n
b1010 m
b111 q
1-
#170000
0-
#175000
b1101111 (
b1101111 @
b1101111 n
b1011 m
b1000 q
1-
#180000
0-
#185000
b1110000 (
b1110000 @
b1110000 n
b1100 m
b1001 q
1-
#190000
0-
#195000
b1110001 (
b1110001 @
b1110001 n
b1101 m
b1100110011001100 *
b1100110011001100 X
1[
b1100110011001100 W
b1100110011001100 _
1)
0!
b1 r
11
b1100110011001100 0
b1100110011001100 :
b100 3
b100 ;
b0 q
1-
#200000
0-
#205000
1!
b1100110011001100 "
b1100110011001100 ^
19
b1110010 (
b1110010 @
b1110010 n
b1110 m
b1100110011001100 ?
b1100110011001100 p
1Y
1)
b1000000010 *
b1000000010 X
b1000000010 W
b1000000010 _
17
b1000000010 6
b1000000010 =
01
b0 q
1-
#210000
0-
#215000
09
1Z
b1110011 (
b1110011 @
b1110011 n
b1111 m
b1000000010 ?
b1000000010 p
1)
b0 *
b0 X
1!
b1000000010 "
b1000000010 ^
0[
b0 W
b0 _
b1010 r
07
b0 q
1-
#220000
0-
#225000
b0 "
b0 ^
b1110100 (
b1110100 @
b1110100 n
b10000 m
b0 ?
b0 p
0Y
b1 q
1-
#230000
0-
#235000
0Z
b1110101 (
b1110101 @
b1110101 n
b10001 m
b10 q
1-
#240000
0-
#245000
b1110110 (
b1110110 @
b1110110 n
b10010 m
b11 q
1-
#250000
0-
#255000
b1110111 (
b1110111 @
b1110111 n
b10011 m
b100 q
1-
#260000
0-
#265000
b1111000 (
b1111000 @
b1111000 n
b10100 m
b101 q
1-
#270000
0-
#275000
b1111001 (
b1111001 @
b1111001 n
b10101 m
b110 q
1-
#280000
0-
#285000
b1111010 (
b1111010 @
b1111010 n
b10110 m
b111 q
1-
#290000
0-
#295000
b1111011 (
b1111011 @
b1111011 n
b10111 m
b1000 q
1-
#300000
0-
#305000
b1111100 (
b1111100 @
b1111100 n
b11000 m
b1001 q
1-
#310000
0-
#315000
b1111101 (
b1111101 @
b1111101 n
b11001 m
b101 r
b0 q
1-
#320000
0-
#325000
b0 o
b1100100 (
b1100100 @
b1100100 n
b0 m
b1 q
1-
#330000
0-
#335000
0!
0>
0'
b10 q
1-
#340000
0-
#345000
b11 q
1-
#350000
0-
#355000
b100 q
1-
#360000
0-
#365000
b101 q
1-
