rtl/router_psum.v
`timescale 1ns / 1ps

module router_psum #( parameter DATA_BITWIDTH = 16,
		      parameter ADDR_BITWIDTH_GLB = 10,
		      parameter ADDR_BITWIDTH_SPAD = 9,
						
		      parameter X_dim = 5,
                      parameter Y_dim = 3,
                      parameter kernel_size = 3,
                      parameter act_size = 5,
						
//		      parameter A_READ_ADDR =100, 
                        
//                    parameter A_LOAD_ADDR = 0,
						
		      parameter PSUM_READ_ADDR = 0,
		      parameter PSUM_LOAD_ADDR = 0
		     )
					
		     (	
		      input clk,
		      input reset,
						
		      //for writing and reading glb
		      input [DATA_BITWIDTH*X_dim-1 : 0] r_data_spad_psum,
		      output reg [ADDR_BITWIDTH_GLB-1 : 0] w_addr_glb_psum,
		      output reg write_en_glb_psum,
						
		      //for writing to spad
		      output reg [DATA_BITWIDTH-1 : 0] w_data_glb_psum,
//		      output reg load_en_spad,
						
		      //Input from PE cluster to write psums to glb
		      input write_psum_ctrl
			
		     );
				
					
		// enum reg [2:0] {IDLE=3'b000, WRITE_GLB=3'b001, READ_PSUM=3'b010} state;
		reg [2:0] state;		
		localparam IDLE=3'b000;
		localparam WRITE_GLB=3'b001;
		localparam READ_PSUM=3'b010;
		reg [4:0] psum_count;
		reg [DATA_BITWIDTH*X_dim-1 : 0] pe_psum;
		reg [2:0] iter;
		
		always@(posedge clk) begin
//			$display("State of router_psum: %s", state.name());
			if(reset) begin
				w_addr_glb_psum <= PSUM_LOAD_ADDR;
				psum_count <= 0;
				write_en_glb_psum <= 0;
				iter <= 0;
				state <= IDLE;
			end else begin
				case(state)
					IDLE:begin
						if(write_psum_ctrl) begin
							//write_en_glb_psum <= 1;
							state <= READ_PSUM;
						end else begin
							psum_count <= 0;
							write_en_glb_psum <= 0;
							w_addr_glb_psum <= PSUM_LOAD_ADDR;
							state <= IDLE;
						end
					end
					
					READ_PSUM:begin
						pe_psum <= r_data_spad_psum;
//						$display("Psum read in router:%d",pe_psum[0:kernel_size-1]);
						psum_count <= 0;
						state <= WRITE_GLB;
					end
					
					WRITE_GLB:begin
						write_en_glb_psum <= 1;
//						$display("Psum written to address %d; Iter is %d",w_addr_glb_psum, iter);
						if(psum_count == (X_dim-1)) begin
							w_data_glb_psum <= pe_psum[(psum_count+1)*DATA_BITWIDTH-1 -: DATA_BITWIDTH];
							psum_count <= 0;
							w_addr_glb_psum <= w_addr_glb_psum + 1;
							iter <= iter + 1;
							state <= IDLE;
						end else begin
							w_data_glb_psum <= pe_psum[(psum_count+1)*DATA_BITWIDTH-1 -: DATA_BITWIDTH];
							psum_count <= psum_count + 1;
							
							if(psum_count == (X_dim-1)) begin
								state <= IDLE;
							end else if(psum_count == 0) begin
								w_addr_glb_psum <= PSUM_LOAD_ADDR+iter*X_dim;
								state <= WRITE_GLB;
							end else begin
								w_addr_glb_psum <= w_addr_glb_psum + 1;
								state <= WRITE_GLB;
							end
							
						end
					end
				endcase
			end
		end
 
endmodule

rtl/router_psum_generic.v
`timescale 1ns / 1ps

module router_generic_psum
#(
    parameter DATA_BITWIDTH      = 16,
    parameter ADDR_BITWIDTH_GLB  = 10,
    parameter ADDR_BITWIDTH_SPAD = 9,

    parameter X_dim       = 5,
    parameter Y_dim       = 3,
    parameter kernel_size = 3,
    parameter act_size    = 5,

    parameter PSUM_READ_ADDR = 0,
    parameter PSUM_LOAD_ADDR = 0,

    // 0=N, 1=S, 2=W, 3=E
    parameter integer COMPUTE_DIR = 3
)
(
    // ---------------- EXACT SAME PORTS ----------------
    input  clk,
    input  reset,
    input  [3:0] router_mode,

    input  [DATA_BITWIDTH*X_dim-1:0] north_data_i,
    input                            north_enable_i,

    output reg [DATA_BITWIDTH*X_dim-1:0] south_data_o,
    output reg                           south_enable_o,

    input  [DATA_BITWIDTH*X_dim-1:0] west_data_i,
    input                            west_enable_i,

    output [DATA_BITWIDTH-1:0]       west_data_o,
    output                           west_enable_o,

    input  [DATA_BITWIDTH*X_dim-1:0] east_data_i,
    input                            east_enable_i,

    output reg [DATA_BITWIDTH*X_dim-1:0] east_data_o,

    output [ADDR_BITWIDTH_GLB-1:0]   w_addr_glb_psum
);

    // -------------------------------------------------
    // Direction constants
    // -------------------------------------------------
    localparam DIR_N = 0;
    localparam DIR_S = 1;
    localparam DIR_W = 2;
    localparam DIR_E = 3;

    // -------------------------------------------------
    // Arbitration (IDENTICAL to router_west_psum)
    // -------------------------------------------------
    reg [DATA_BITWIDTH*X_dim-1:0] data_out;

    always @(*) begin
        if (north_enable_i)
            data_out = north_data_i;
        else if (west_enable_i)
            data_out = west_data_i;
        else
            data_out = 0;
    end

    // -------------------------------------------------
    // Routing modes (IDENTICAL behavior)
    // -------------------------------------------------
    localparam SOUTH     = 2;
    localparam EAST      = 4;
    localparam EASTSOUTH = 6;
    localparam CLOSED    = 11;

    always @(*) begin
        south_data_o   = 0;
        south_enable_o = 0;
        east_data_o    = 0;

        case (router_mode)
            SOUTH: begin
                south_data_o   = data_out;
                south_enable_o = north_enable_i | west_enable_i;
            end

            EAST: begin
                east_data_o = data_out;
            end

            EASTSOUTH: begin
                south_data_o   = data_out;
                south_enable_o = north_enable_i | west_enable_i;
                east_data_o    = data_out;
            end

            CLOSED: begin
                // no outputs
            end
        endcase
    end

    // -------------------------------------------------
    // COMPUTE-DIR SELECTED PSUM SOURCE
    // -------------------------------------------------
    wire [DATA_BITWIDTH*X_dim-1:0] psum_data_src =
        (COMPUTE_DIR == DIR_N) ? north_data_i :
        (COMPUTE_DIR == DIR_W) ? west_data_i  :
        (COMPUTE_DIR == DIR_E) ? east_data_i  :
                                 0;

    wire psum_enable_src =
        (COMPUTE_DIR == DIR_N) ? north_enable_i :
        (COMPUTE_DIR == DIR_W) ? west_enable_i  :
        (COMPUTE_DIR == DIR_E) ? east_enable_i  :
                                 1'b0;

    // -------------------------------------------------
    // PSUM MODULE (UNMODIFIED, REUSED)
    // -------------------------------------------------
    router_psum #(
        .DATA_BITWIDTH(DATA_BITWIDTH),
        .ADDR_BITWIDTH_GLB(ADDR_BITWIDTH_GLB),
        .ADDR_BITWIDTH_SPAD(ADDR_BITWIDTH_SPAD),
        .X_dim(X_dim),
        .Y_dim(Y_dim),
        .kernel_size(kernel_size),
        .act_size(act_size),
        .PSUM_READ_ADDR(PSUM_READ_ADDR),
        .PSUM_LOAD_ADDR(PSUM_LOAD_ADDR)
    ) router_psum_0 (
        .clk(clk),
        .reset(reset),
        .r_data_spad_psum(psum_data_src),
        .w_addr_glb_psum(w_addr_glb_psum),
        .write_en_glb_psum(west_enable_o),
        .w_data_glb_psum(west_data_o),
        .write_psum_ctrl(psum_enable_src)
    );

endmodule

testbench/router_psum_tb.v
`timescale 1ns/1ps

module tb_router_generic_psum;

    // -------------------------------------------------
    // Parameters (match DUT)
    // -------------------------------------------------
    localparam DATA_BITWIDTH     = 16;
    localparam X_dim             = 5;
    localparam ADDR_BITWIDTH_GLB = 10;

    // -------------------------------------------------
    // DUT signals (EXACT drop-in interface)
    // -------------------------------------------------
    reg clk;
    reg reset;
    reg [3:0] router_mode;

    reg  [DATA_BITWIDTH*X_dim-1:0] north_data_i;
    reg                            north_enable_i;

    wire [DATA_BITWIDTH*X_dim-1:0] south_data_o;
    wire                           south_enable_o;

    reg  [DATA_BITWIDTH*X_dim-1:0] west_data_i;
    reg                            west_enable_i;

    wire [DATA_BITWIDTH-1:0]       west_data_o;
    wire                           west_enable_o;

    reg  [DATA_BITWIDTH*X_dim-1:0] east_data_i;
    reg                            east_enable_i;

    wire [DATA_BITWIDTH*X_dim-1:0] east_data_o;

    wire [ADDR_BITWIDTH_GLB-1:0]   w_addr_glb_psum;

    // -------------------------------------------------
    // DUT instance
    // COMPUTE_DIR = EAST (drop-in match)
    // -------------------------------------------------
    router_generic_psum #(
        .DATA_BITWIDTH(DATA_BITWIDTH),
        .X_dim(X_dim),
        .ADDR_BITWIDTH_GLB(ADDR_BITWIDTH_GLB),
        .COMPUTE_DIR(3) // EAST
    ) dut (
        .clk(clk),
        .reset(reset),
        .router_mode(router_mode),

        .north_data_i(north_data_i),
        .north_enable_i(north_enable_i),

        .south_data_o(south_data_o),
        .south_enable_o(south_enable_o),

        .west_data_i(west_data_i),
        .west_enable_i(west_enable_i),

        .west_data_o(west_data_o),
        .west_enable_o(west_enable_o),

        .east_data_i(east_data_i),
        .east_enable_i(east_enable_i),

        .east_data_o(east_data_o),

        .w_addr_glb_psum(w_addr_glb_psum)
    );

    // -------------------------------------------------
    // Clock (100 MHz)
    // -------------------------------------------------
    always #5 clk = ~clk;

    // -------------------------------------------------
    // VCD dump
    // -------------------------------------------------
    initial begin
        $dumpfile("router_generic_psum_tb.vcd");
        $dumpvars(0, tb_router_generic_psum);
    end

    // -------------------------------------------------
    // Helpers
    // -------------------------------------------------
    task clear_inputs;
        begin
            north_enable_i = 0;
            west_enable_i  = 0;
            east_enable_i  = 0;
            north_data_i   = 0;
            west_data_i    = 0;
            east_data_i    = 0;
        end
    endtask

    task wait_clk(input integer n);
        integer i;
        begin
            for (i = 0; i < n; i = i + 1)
                @(posedge clk);
        end
    endtask

    // -------------------------------------------------
    // Test sequence
    // -------------------------------------------------
    initial begin
        clk   = 0;
        reset = 1;
        router_mode = 0;
        clear_inputs();

        // -------- Reset --------
        wait_clk(3);
        reset = 0;
        wait_clk(2);

        // =================================================
        // TEST 1: NORTH priority over WEST → SOUTH
        // =================================================
        router_mode = 2; // SOUTH
        north_data_i   = {X_dim{16'hAAAA}};
        west_data_i    = {X_dim{16'hBBBB}};
        north_enable_i = 1;
        west_enable_i  = 1;

        wait_clk(2);
        clear_inputs();

        // =================================================
        // TEST 2: WEST only → SOUTH
        // =================================================
        router_mode = 2; // SOUTH
        west_data_i   = {X_dim{16'hCCCC}};
        west_enable_i = 1;

        wait_clk(2);
        clear_inputs();

        // =================================================
        // TEST 3: EASTSOUTH broadcast
        // =================================================
        router_mode = 6; // EASTSOUTH
        north_data_i   = {X_dim{16'hDDDD}};
        north_enable_i = 1;

        wait_clk(2);
        clear_inputs();

        // =================================================
        // TEST 4: CLOSED mode
        // =================================================
        router_mode = 11; // CLOSED
        north_data_i   = {X_dim{16'hEEEE}};
        north_enable_i = 1;

        wait_clk(2);
        clear_inputs();

        // =================================================
        // TEST 5: PSUM drain (single trigger)
        // =================================================
        east_data_i = {
            16'h0005,
            16'h0004,
            16'h0003,
            16'h0002,
            16'h0001
        };

        east_enable_i = 1;
        wait_clk(1);
        east_enable_i = 0;

        wait_clk(12);

        // =================================================
        // TEST 6: Back-to-back PSUM triggers
        // =================================================
        east_data_i = {
            16'h0015,
            16'h0014,
            16'h0013,
            16'h0012,
            16'h0011
        };

        east_enable_i = 1;
        wait_clk(1);
        east_enable_i = 0;

        wait_clk(8);

        east_data_i = {
            16'h0025,
            16'h0024,
            16'h0023,
            16'h0022,
            16'h0021
        };

        east_enable_i = 1;
        wait_clk(1);
        east_enable_i = 0;

        wait_clk(15);

        $finish;
    end

endmodule

router_generic_psum_tb.vcd
$date
	Sun Dec 14 18:20:58 2025
$end
$version
	Icarus Verilog
$end
$timescale
	1ps
$end
$scope module tb_router_generic_psum $end
$var wire 1 ! west_enable_o $end
$var wire 16 " west_data_o [15:0] $end
$var wire 10 # w_addr_glb_psum [9:0] $end
$var wire 1 $ south_enable_o $end
$var wire 80 % south_data_o [79:0] $end
$var wire 80 & east_data_o [79:0] $end
$var parameter 32 ' ADDR_BITWIDTH_GLB $end
$var parameter 32 ( DATA_BITWIDTH $end
$var parameter 32 ) X_dim $end
$var reg 1 * clk $end
$var reg 80 + east_data_i [79:0] $end
$var reg 1 , east_enable_i $end
$var reg 80 - north_data_i [79:0] $end
$var reg 1 . north_enable_i $end
$var reg 1 / reset $end
$var reg 4 0 router_mode [3:0] $end
$var reg 80 1 west_data_i [79:0] $end
$var reg 1 2 west_enable_i $end
$scope module dut $end
$var wire 1 * clk $end
$var wire 80 3 east_data_i [79:0] $end
$var wire 1 , east_enable_i $end
$var wire 80 4 north_data_i [79:0] $end
$var wire 1 . north_enable_i $end
$var wire 80 5 psum_data_src [79:0] $end
$var wire 1 6 psum_enable_src $end
$var wire 1 / reset $end
$var wire 4 7 router_mode [3:0] $end
$var wire 80 8 west_data_i [79:0] $end
$var wire 1 2 west_enable_i $end
$var wire 1 ! west_enable_o $end
$var wire 16 9 west_data_o [15:0] $end
$var wire 10 : w_addr_glb_psum [9:0] $end
$var parameter 32 ; ADDR_BITWIDTH_GLB $end
$var parameter 32 < ADDR_BITWIDTH_SPAD $end
$var parameter 32 = CLOSED $end
$var parameter 32 > COMPUTE_DIR $end
$var parameter 32 ? DATA_BITWIDTH $end
$var parameter 32 @ DIR_E $end
$var parameter 32 A DIR_N $end
$var parameter 32 B DIR_S $end
$var parameter 32 C DIR_W $end
$var parameter 32 D EAST $end
$var parameter 32 E EASTSOUTH $end
$var parameter 32 F PSUM_LOAD_ADDR $end
$var parameter 32 G PSUM_READ_ADDR $end
$var parameter 32 H SOUTH $end
$var parameter 32 I X_dim $end
$var parameter 32 J Y_dim $end
$var parameter 32 K act_size $end
$var parameter 32 L kernel_size $end
$var reg 80 M data_out [79:0] $end
$var reg 80 N east_data_o [79:0] $end
$var reg 80 O south_data_o [79:0] $end
$var reg 1 $ south_enable_o $end
$scope module router_psum_0 $end
$var wire 1 * clk $end
$var wire 80 P r_data_spad_psum [79:0] $end
$var wire 1 / reset $end
$var wire 1 6 write_psum_ctrl $end
$var parameter 32 Q ADDR_BITWIDTH_GLB $end
$var parameter 32 R ADDR_BITWIDTH_SPAD $end
$var parameter 32 S DATA_BITWIDTH $end
$var parameter 3 T IDLE $end
$var parameter 32 U PSUM_LOAD_ADDR $end
$var parameter 32 V PSUM_READ_ADDR $end
$var parameter 3 W READ_PSUM $end
$var parameter 3 X WRITE_GLB $end
$var parameter 32 Y X_dim $end
$var parameter 32 Z Y_dim $end
$var parameter 32 [ act_size $end
$var parameter 32 \ kernel_size $end
$var reg 3 ] iter [2:0] $end
$var reg 80 ^ pe_psum [79:0] $end
$var reg 5 _ psum_count [4:0] $end
$var reg 3 ` state [2:0] $end
$var reg 10 a w_addr_glb_psum [9:0] $end
$var reg 16 b w_data_glb_psum [15:0] $end
$var reg 1 ! write_en_glb_psum $end
$upscope $end
$upscope $end
$scope task clear_inputs $end
$upscope $end
$scope task wait_clk $end
$var integer 32 c i [31:0] $end
$var integer 32 d n [31:0] $end
$upscope $end
$upscope $end
$enddefinitions $end
$comment Show the parameter values. $end
$dumpall
b11 \
b101 [
b11 Z
b101 Y
b1 X
b10 W
b0 V
b0 U
b0 T
b10000 S
b1001 R
b1010 Q
b11 L
b101 K
b11 J
b101 I
b10 H
b0 G
b0 F
b110 E
b100 D
b10 C
b1 B
b0 A
b11 @
b10000 ?
b11 >
b1011 =
b1001 <
b1010 ;
b101 )
b10000 (
b1010 '
$end
#0
$dumpvars
b11 d
b0 c
bx b
bx a
bx `
bx _
bx ^
bx ]
b0 P
b0 O
b0 N
b0 M
bx :
bx 9
b0 8
b0 7
06
b0 5
b0 4
b0 3
02
b0 1
b0 0
1/
0.
b0 -
0,
b0 +
0*
b0 &
b0 %
0$
bx #
bx "
x!
$end
#5000
b0 `
b0 ]
0!
b0 _
b0 #
b0 :
b0 a
b1 c
1*
#10000
0*
#15000
b10 c
1*
#20000
0*
#25000
b10 d
0/
b0 c
1*
#30000
0*
#35000
b1 c
1*
#40000
0*
#45000
b10101010101010101010101010101010101010101010101010101010101010101010101010101010 %
b10101010101010101010101010101010101010101010101010101010101010101010101010101010 O
b10101010101010101010101010101010101010101010101010101010101010101010101010101010 M
1$
12
1.
b10111011101110111011101110111011101110111011101110111011101110111011101110111011 1
b10111011101110111011101110111011101110111011101110111011101110111011101110111011 8
b10101010101010101010101010101010101010101010101010101010101010101010101010101010 -
b10101010101010101010101010101010101010101010101010101010101010101010101010101010 4
b10 0
b10 7
b0 c
1*
#50000
0*
#55000
b1 c
1*
#60000
0*
#65000
1$
b11001100110011001100110011001100110011001100110011001100110011001100110011001100 %
b11001100110011001100110011001100110011001100110011001100110011001100110011001100 O
b11001100110011001100110011001100110011001100110011001100110011001100110011001100 M
b11001100110011001100110011001100110011001100110011001100110011001100110011001100 1
b11001100110011001100110011001100110011001100110011001100110011001100110011001100 8
b0 -
b0 4
12
0.
b0 c
1*
#70000
0*
#75000
b1 c
1*
#80000
0*
#85000
b11011101110111011101110111011101110111011101110111011101110111011101110111011101 &
b11011101110111011101110111011101110111011101110111011101110111011101110111011101 N
1$
b11011101110111011101110111011101110111011101110111011101110111011101110111011101 %
b11011101110111011101110111011101110111011101110111011101110111011101110111011101 O
b11011101110111011101110111011101110111011101110111011101110111011101110111011101 M
1.
b11011101110111011101110111011101110111011101110111011101110111011101110111011101 -
b11011101110111011101110111011101110111011101110111011101110111011101110111011101 4
b110 0
b110 7
b0 1
b0 8
02
b0 c
1*
#90000
0*
#95000
b1 c
1*
#100000
0*
#105000
b0 &
b0 N
0$
b0 %
b0 O
b11101110111011101110111011101110111011101110111011101110111011101110111011101110 M
b1011 0
b1011 7
b11101110111011101110111011101110111011101110111011101110111011101110111011101110 -
b11101110111011101110111011101110111011101110111011101110111011101110111011101110 4
1.
b0 c
1*
#110000
0*
#115000
b1 c
1*
#120000
0*
#125000
b0 M
b1 d
16
1,
b1010000000000000100000000000000001100000000000000100000000000000001 5
b1010000000000000100000000000000001100000000000000100000000000000001 P
b1010000000000000100000000000000001100000000000000100000000000000001 +
b1010000000000000100000000000000001100000000000000100000000000000001 3
b0 -
b0 4
0.
b0 c
1*
#130000
0*
#135000
b10 `
b1100 d
06
0,
b0 c
1*
#140000
0*
#145000
b1 `
b1010000000000000100000000000000001100000000000000100000000000000001 ^
b1 c
1*
#150000
0*
#155000
b1 _
b1 "
b1 9
b1 b
1!
b10 c
1*
#160000
0*
#165000
b1 #
b1 :
b1 a
b10 _
b10 "
b10 9
b10 b
b11 c
1*
#170000
0*
#175000
b10 #
b10 :
b10 a
b11 _
b11 "
b11 9
b11 b
b100 c
1*
#180000
0*
#185000
b11 #
b11 :
b11 a
b100 _
b100 "
b100 9
b100 b
b101 c
1*
#190000
0*
#195000
b0 `
b1 ]
b100 #
b100 :
b100 a
b0 _
b101 "
b101 9
b101 b
b110 c
1*
#200000
0*
#205000
b0 #
b0 :
b0 a
0!
b111 c
1*
#210000
0*
#215000
b1000 c
1*
#220000
0*
#225000
b1001 c
1*
#230000
0*
#235000
b1010 c
1*
#240000
0*
#245000
b1011 c
1*
#250000
0*
#255000
b1 d
16
1,
b101010000000000010100000000000001001100000000000100100000000000010001 5
b101010000000000010100000000000001001100000000000100100000000000010001 P
b101010000000000010100000000000001001100000000000100100000000000010001 +
b101010000000000010100000000000001001100000000000100100000000000010001 3
b0 c
1*
#260000
0*
#265000
b10 `
b1000 d
06
0,
b0 c
1*
#270000
0*
#275000
b1 `
b101010000000000010100000000000001001100000000000100100000000000010001 ^
b1 c
1*
#280000
0*
#285000
b101 #
b101 :
b101 a
b1 _
b10001 "
b10001 9
b10001 b
1!
b10 c
1*
#290000
0*
#295000
b110 #
b110 :
b110 a
b10 _
b10010 "
b10010 9
b10010 b
b11 c
1*
#300000
0*
#305000
b111 #
b111 :
b111 a
b11 _
b10011 "
b10011 9
b10011 b
b100 c
1*
#310000
0*
#315000
b1000 #
b1000 :
b1000 a
b100 _
b10100 "
b10100 9
b10100 b
b101 c
1*
#320000
0*
#325000
b0 `
b10 ]
b1001 #
b1001 :
b1001 a
b0 _
b10101 "
b10101 9
b10101 b
b110 c
1*
#330000
0*
#335000
b0 #
b0 :
b0 a
0!
b111 c
1*
#340000
0*
#345000
b1 d
16
1,
b1001010000000000100100000000000010001100000000001000100000000000100001 5
b1001010000000000100100000000000010001100000000001000100000000000100001 P
b1001010000000000100100000000000010001100000000001000100000000000100001 +
b1001010000000000100100000000000010001100000000001000100000000000100001 3
b0 c
1*
#350000
0*
#355000
b10 `
b1111 d
06
0,
b0 c
1*
#360000
0*
#365000
b1 `
b1001010000000000100100000000000010001100000000001000100000000000100001 ^
b1 c
1*
#370000
0*
#375000
b1010 #
b1010 :
b1010 a
b1 _
b100001 "
b100001 9
b100001 b
1!
b10 c
1*
#380000
0*
#385000
b1011 #
b1011 :
b1011 a
b10 _
b100010 "
b100010 9
b100010 b
b11 c
1*
#390000
0*
#395000
b1100 #
b1100 :
b1100 a
b11 _
b100011 "
b100011 9
b100011 b
b100 c
1*
#400000
0*
#405000
b1101 #
b1101 :
b1101 a
b100 _
b100100 "
b100100 9
b100100 b
b101 c
1*
#410000
0*
#415000
b0 `
b11 ]
b1110 #
b1110 :
b1110 a
b0 _
b100101 "
b100101 9
b100101 b
b110 c
1*
#420000
0*
#425000
b0 #
b0 :
b0 a
0!
b111 c
1*
#430000
0*
#435000
b1000 c
1*
#440000
0*
#445000
b1001 c
1*
#450000
0*
#455000
b1010 c
1*
#460000
0*
#465000
b1011 c
1*
#470000
0*
#475000
b1100 c
1*
#480000
0*
#485000
b1101 c
1*
#490000
0*
#495000
b1110 c
1*
#500000
0*
#505000
b1111 c
1*
