rtl/router_weight.v
`timescale 1ns / 1ps

module router_weight #(
    parameter DATA_BITWIDTH      = 16,
    parameter ADDR_BITWIDTH_GLB  = 10,
    parameter ADDR_BITWIDTH_SPAD = 9,

    parameter X_dim       = 5,
    parameter Y_dim       = 3,
    parameter kernel_size = 3,
    parameter act_size    = 5,   // unused but kept for compatibility

    parameter W_READ_ADDR = 0, 
    parameter W_LOAD_ADDR = 0    // currently unused (SPAD addr handled elsewhere)
)
(
    input clk,
    input reset,

    // for reading GLB
    input  [DATA_BITWIDTH-1:0]          r_data_glb_wght,
    output reg [ADDR_BITWIDTH_GLB-1:0]  r_addr_glb_wght,
    output reg                          read_req_glb_wght,

    // for writing to SPAD
    output reg [DATA_BITWIDTH-1:0]      w_data_spad,
    output reg                          load_en_spad,

    // control: start loading weights to SPAD
    input                               load_spad_ctrl
);

    // FSM states
    reg [2:0] state;
    localparam IDLE       = 3'b000;
    localparam READ_GLB   = 3'b001;
    localparam WRITE_SPAD = 3'b010;

    // total weights in one kernel block
    localparam integer TOTAL_WEIGHTS = kernel_size * kernel_size;

    // counter for how many weights processed
    reg [5:0] filt_count;  // enough for up to 64 weights; grow if needed

    always @(posedge clk or posedge reset) begin
        if (reset) begin
            read_req_glb_wght <= 1'b0;
            r_addr_glb_wght   <= {ADDR_BITWIDTH_GLB{1'b0}};
            load_en_spad      <= 1'b0;
            w_data_spad       <= {DATA_BITWIDTH{1'b0}};
            filt_count        <= 6'd0;
            state             <= IDLE;
        end else begin
            // default
            load_en_spad <= 1'b0;

            case (state)

                //--------------------------------------------------
                // IDLE – wait for load_spad_ctrl pulse
                //--------------------------------------------------
                IDLE: begin
                    read_req_glb_wght <= 1'b0;
                    filt_count        <= 6'd0;

                    if (load_spad_ctrl) begin
                        read_req_glb_wght <= 1'b1;
                        r_addr_glb_wght   <= W_READ_ADDR[ADDR_BITWIDTH_GLB-1:0];
                        state             <= READ_GLB;
                    end
                end

                //--------------------------------------------------
                // READ_GLB – latch GLB data into local buffer
                //--------------------------------------------------
                READ_GLB: begin
                    w_data_spad <= r_data_glb_wght;  // combinational GLB
                    state       <= WRITE_SPAD;
                end

                //--------------------------------------------------
                // WRITE_SPAD – pulse write enable, advance or finish
                //--------------------------------------------------
                WRITE_SPAD: begin
                    load_en_spad <= 1'b1;

                    if (filt_count == (TOTAL_WEIGHTS - 1)) begin
                        // last weight written
                        read_req_glb_wght <= 1'b0;
                        filt_count        <= 6'd0;
                        state             <= IDLE;
                    end else begin
                        // more weights to go
                        filt_count      <= filt_count + 6'd1;
                        r_addr_glb_wght <= r_addr_glb_wght + 1'b1;
                        state           <= READ_GLB;
                    end
                end

                default: begin
                    state <= IDLE;
                end

            endcase
        end
    end

endmodule

rtl/router_weight_generic.v
`timescale 1ns / 1ps

module router_generic_wght
#(
    parameter DATA_BITWIDTH      = 16,
    parameter ADDR_BITWIDTH_GLB  = 10,
    parameter ADDR_BITWIDTH_SPAD = 9,

    parameter X_dim       = 5,
    parameter Y_dim       = 3,
    parameter kernel_size = 3,
    parameter act_size    = 5,

    parameter W_READ_ADDR = 0,
    parameter W_LOAD_ADDR = 0,

    // Compute direction:
    // 0 = NORTH, 1 = SOUTH, 2 = WEST, 3 = EAST
    parameter integer COMPUTE_DIR = 2
)
(
    input clk,
    input reset,

    input [3:0] router_mode,

    // GLB read interface
    output [ADDR_BITWIDTH_GLB-1:0] glb_addr_read_wght,
    output                         glb_req_read_wght,

    // Directional inputs
    input [DATA_BITWIDTH-1:0] north_data_i,
    input                      north_enable_i,

    input [DATA_BITWIDTH-1:0] south_data_i,
    input                      south_enable_i,

    input [DATA_BITWIDTH-1:0] west_data_i,
    input                      west_enable_i,

    input [DATA_BITWIDTH-1:0] east_data_i,
    input                      east_enable_i,

    // Directional outputs
    output reg [DATA_BITWIDTH-1:0] north_data_o,
    output reg                     north_enable_o,

    output reg [DATA_BITWIDTH-1:0] south_data_o,
    output reg                     south_enable_o,

    output reg [DATA_BITWIDTH-1:0] west_data_o,
    output reg                     west_enable_o,

    output reg [DATA_BITWIDTH-1:0] east_data_o,
    output reg                     east_enable_o
);

    // --------------------------------------------------
    // 1. Input arbitration (EXACT priority)
    // north > south > west > east
    // --------------------------------------------------
    reg [DATA_BITWIDTH-1:0] data_out;
    reg load_spad_ctrl_c;

    always @(*) begin
        if (north_enable_i) begin
            data_out         = north_data_i;
            load_spad_ctrl_c = 1'b1;
        end else if (south_enable_i) begin
            data_out         = south_data_i;
            load_spad_ctrl_c = 1'b1;
        end else if (west_enable_i) begin
            data_out         = west_data_i;
            load_spad_ctrl_c = 1'b1;
        end else if (east_enable_i) begin
            data_out         = east_data_i;
            load_spad_ctrl_c = 1'b1;
        end else begin
            data_out         = {DATA_BITWIDTH{1'b0}};
            load_spad_ctrl_c = 1'b0;
        end
    end

    // --------------------------------------------------
    // 2. One-shot load pulse (EDGE-triggered)
    // EXACT match to router_west_wght
    // --------------------------------------------------
    reg load_ff0, load_ff1;
    wire load_spad_ctrl;

    assign load_spad_ctrl = load_ff0 & ~load_ff1;

    always @(posedge clk) begin
        if (reset) begin
            load_ff0 <= 1'b0;
            load_ff1 <= 1'b0;
        end else begin
            load_ff0 <= load_spad_ctrl_c;
            load_ff1 <= load_ff0;
        end
    end

    // --------------------------------------------------
    // 3. Weight loader FSM (UNCHANGED)
    // --------------------------------------------------
    wire [DATA_BITWIDTH-1:0] spad_data_o;
    wire                     spad_en_o;

    router_weight #(
        .DATA_BITWIDTH(DATA_BITWIDTH),
        .ADDR_BITWIDTH_GLB(ADDR_BITWIDTH_GLB),
        .ADDR_BITWIDTH_SPAD(ADDR_BITWIDTH_SPAD),
        .X_dim(X_dim),
        .Y_dim(Y_dim),
        .kernel_size(kernel_size),
        .act_size(act_size),
        .W_READ_ADDR(W_READ_ADDR),
        .W_LOAD_ADDR(W_LOAD_ADDR)
    ) router_weight_0 (
        .clk(clk),
        .reset(reset),

        // NOTE: EXACT west behavior — FSM sees data_out
        .r_data_glb_wght(data_out),
        .r_addr_glb_wght(glb_addr_read_wght),
        .read_req_glb_wght(glb_req_read_wght),

        .w_data_spad(spad_data_o),
        .load_en_spad(spad_en_o),

        .load_spad_ctrl(load_spad_ctrl)
    );

    // --------------------------------------------------
    // 4. STRUCTURAL SPAD binding to COMPUTE_DIR
    // SPAD output is NEVER gated by router_mode
    // --------------------------------------------------
    always @(*) begin
        north_data_o   = {DATA_BITWIDTH{1'b0}};
        south_data_o   = {DATA_BITWIDTH{1'b0}};
        west_data_o    = {DATA_BITWIDTH{1'b0}};
        east_data_o    = {DATA_BITWIDTH{1'b0}};

        north_enable_o = 1'b0;
        south_enable_o = 1'b0;
        west_enable_o  = 1'b0;
        east_enable_o  = 1'b0;

        case (COMPUTE_DIR)
            0: begin north_data_o = spad_data_o; north_enable_o = spad_en_o; end
            1: begin south_data_o = spad_data_o; south_enable_o = spad_en_o; end
            2: begin west_data_o  = spad_data_o; west_enable_o  = spad_en_o; end
            3: begin east_data_o  = spad_data_o; east_enable_o  = spad_en_o; end
        endcase
    end

    // --------------------------------------------------
    // 5. Routing logic (EXACT semantics)
    // Routing NEVER blocks SPAD
    // --------------------------------------------------
    localparam ALL        = 0;
    localparam NORTH      = 1;
    localparam SOUTH      = 2;
    localparam WEST       = 3;
    localparam EAST       = 4;
    localparam EASTNORTH  = 5;
    localparam EASTSOUTH  = 6;
    localparam EASTWEST   = 7;
    localparam WESTNORTH  = 8;
    localparam WESTSOUTH  = 9;
    localparam WESTEAST   = 10;
    localparam CLOSED     = 11;

    always @(*) begin
        if (router_mode == CLOSED)
            ; // routing suppressed, SPAD unaffected
        else begin
            case (router_mode)
                ALL: begin
                    north_data_o = data_out; north_enable_o = 1;
                    south_data_o = data_out; south_enable_o = 1;
                    east_data_o  = data_out; east_enable_o  = 1;
                end
                NORTH: begin north_data_o = data_out; north_enable_o = 1; end
                SOUTH: begin south_data_o = data_out; south_enable_o = 1; end
                EAST:  begin east_data_o  = data_out; east_enable_o  = 1; end
                EASTNORTH: begin
                    east_data_o  = data_out; east_enable_o  = 1;
                    north_data_o = data_out; north_enable_o = 1;
                end
                EASTSOUTH: begin
                    east_data_o  = data_out; east_enable_o  = 1;
                    south_data_o = data_out; south_enable_o = 1;
                end
                WESTNORTH: begin
                    west_data_o  = data_out; west_enable_o  = 1;
                    north_data_o = data_out; north_enable_o = 1;
                end
                WESTSOUTH: begin
                    west_data_o  = data_out; west_enable_o  = 1;
                    south_data_o = data_out; south_enable_o = 1;
                end
                WESTEAST: begin
                    west_data_o  = data_out; west_enable_o  = 1;
                    east_data_o  = data_out; east_enable_o  = 1;
                end
            endcase
        end
    end

endmodule

testbench/router_weight_tb.v
`timescale 1ns/1ps

module tb_router_generic_wght;

    // -------------------------------------------------
    // Parameters
    // -------------------------------------------------
    localparam DATA_BITWIDTH = 16;
    localparam ADDR_BITWIDTH_GLB = 10;
    localparam DIR_W = 2;  // COMPUTE_DIR = WEST

    // -------------------------------------------------
    // DUT signals
    // -------------------------------------------------
    reg clk;
    reg reset;
    reg [3:0] router_mode;

    reg [DATA_BITWIDTH-1:0] north_data_i;
    reg north_enable_i;

    reg [DATA_BITWIDTH-1:0] south_data_i;
    reg south_enable_i;

    reg [DATA_BITWIDTH-1:0] west_data_i;
    reg west_enable_i;

    reg [DATA_BITWIDTH-1:0] east_data_i;
    reg east_enable_i;

    wire [ADDR_BITWIDTH_GLB-1:0] glb_addr_read_wght;
    wire glb_req_read_wght;

    wire [DATA_BITWIDTH-1:0] north_data_o;
    wire north_enable_o;

    wire [DATA_BITWIDTH-1:0] south_data_o;
    wire south_enable_o;

    wire [DATA_BITWIDTH-1:0] west_data_o;
    wire west_enable_o;

    wire [DATA_BITWIDTH-1:0] east_data_o;
    wire east_enable_o;

    // -------------------------------------------------
    // DUT
    // -------------------------------------------------
    router_generic_wght #(
        .DATA_BITWIDTH(DATA_BITWIDTH),
        .ADDR_BITWIDTH_GLB(ADDR_BITWIDTH_GLB),
        .kernel_size(3),
        .W_READ_ADDR(10'h040),
        .COMPUTE_DIR(DIR_W)
    ) dut (
        .clk(clk),
        .reset(reset),
        .router_mode(router_mode),

        .glb_addr_read_wght(glb_addr_read_wght),
        .glb_req_read_wght(glb_req_read_wght),

        .north_data_i(north_data_i),
        .north_enable_i(north_enable_i),

        .south_data_i(south_data_i),
        .south_enable_i(south_enable_i),

        .west_data_i(west_data_i),
        .west_enable_i(west_enable_i),

        .east_data_i(east_data_i),
        .east_enable_i(east_enable_i),

        .north_data_o(north_data_o),
        .north_enable_o(north_enable_o),

        .south_data_o(south_data_o),
        .south_enable_o(south_enable_o),

        .west_data_o(west_data_o),
        .west_enable_o(west_enable_o),

        .east_data_o(east_data_o),
        .east_enable_o(east_enable_o)
    );

    // -------------------------------------------------
    // Clock
    // -------------------------------------------------
    always #5 clk = ~clk;

    // -------------------------------------------------
    // Wave dump
    // -------------------------------------------------
    initial begin
        $dumpfile("router_generic_wght.vcd");
        $dumpvars(0, tb_router_generic_wght);
    end

    // -------------------------------------------------
    // Stimulus
    // -------------------------------------------------
    initial begin
        clk = 0;
        reset = 1;

        router_mode = 0;

        north_data_i = 0; north_enable_i = 0;
        south_data_i = 0; south_enable_i = 0;
        west_data_i  = 0; west_enable_i  = 0;
        east_data_i  = 0; east_enable_i  = 0;

        #20 reset = 0;

        // -------------------------------------------------
        // TEST 1: Routing only (north -> south)
        // -------------------------------------------------
        $display("TEST 1: routing north to south");
        router_mode = 4'd2; // SOUTH

        north_data_i   = 16'h1111;
        north_enable_i = 1;
        #10;
        north_enable_i = 0;

        #40;

        // -------------------------------------------------
        // TEST 2: Weight load triggered from EAST
        // Routing continues in parallel
        // -------------------------------------------------
        $display("TEST 2: weight load + routing");
        router_mode = 4'd1; // NORTH

        east_data_i   = 16'hAAAA;
        east_enable_i = 1;
        #10;
        east_enable_i = 0;

        #120;

        // -------------------------------------------------
        // TEST 3: Second kernel load
        // -------------------------------------------------
        $display("TEST 3: second kernel");
        east_data_i   = 16'h5555;
        east_enable_i = 1;
        #10;
        east_enable_i = 0;

        #120;

        $display("Simulation complete");
        $finish;
    end

endmodule

router_generic_wght.vcd
$date
	Sun Dec 14 18:34:08 2025
$end
$version
	Icarus Verilog
$end
$timescale
	1ps
$end
$scope module tb_router_generic_wght $end
$var wire 1 ! west_enable_o $end
$var wire 16 " west_data_o [15:0] $end
$var wire 1 # south_enable_o $end
$var wire 16 $ south_data_o [15:0] $end
$var wire 1 % north_enable_o $end
$var wire 16 & north_data_o [15:0] $end
$var wire 1 ' glb_req_read_wght $end
$var wire 10 ( glb_addr_read_wght [9:0] $end
$var wire 1 ) east_enable_o $end
$var wire 16 * east_data_o [15:0] $end
$var parameter 32 + ADDR_BITWIDTH_GLB $end
$var parameter 32 , DATA_BITWIDTH $end
$var parameter 32 - DIR_W $end
$var reg 1 . clk $end
$var reg 16 / east_data_i [15:0] $end
$var reg 1 0 east_enable_i $end
$var reg 16 1 north_data_i [15:0] $end
$var reg 1 2 north_enable_i $end
$var reg 1 3 reset $end
$var reg 4 4 router_mode [3:0] $end
$var reg 16 5 south_data_i [15:0] $end
$var reg 1 6 south_enable_i $end
$var reg 16 7 west_data_i [15:0] $end
$var reg 1 8 west_enable_i $end
$scope module dut $end
$var wire 1 . clk $end
$var wire 16 9 east_data_i [15:0] $end
$var wire 1 0 east_enable_i $end
$var wire 1 : load_spad_ctrl $end
$var wire 16 ; north_data_i [15:0] $end
$var wire 1 2 north_enable_i $end
$var wire 1 3 reset $end
$var wire 4 < router_mode [3:0] $end
$var wire 16 = south_data_i [15:0] $end
$var wire 1 6 south_enable_i $end
$var wire 16 > west_data_i [15:0] $end
$var wire 1 8 west_enable_i $end
$var wire 1 ? spad_en_o $end
$var wire 16 @ spad_data_o [15:0] $end
$var wire 1 ' glb_req_read_wght $end
$var wire 10 A glb_addr_read_wght [9:0] $end
$var parameter 32 B ADDR_BITWIDTH_GLB $end
$var parameter 32 C ADDR_BITWIDTH_SPAD $end
$var parameter 32 D ALL $end
$var parameter 32 E CLOSED $end
$var parameter 32 F COMPUTE_DIR $end
$var parameter 32 G DATA_BITWIDTH $end
$var parameter 32 H EAST $end
$var parameter 32 I EASTNORTH $end
$var parameter 32 J EASTSOUTH $end
$var parameter 32 K EASTWEST $end
$var parameter 32 L NORTH $end
$var parameter 32 M SOUTH $end
$var parameter 32 N WEST $end
$var parameter 32 O WESTEAST $end
$var parameter 32 P WESTNORTH $end
$var parameter 32 Q WESTSOUTH $end
$var parameter 32 R W_LOAD_ADDR $end
$var parameter 10 S W_READ_ADDR $end
$var parameter 32 T X_dim $end
$var parameter 32 U Y_dim $end
$var parameter 32 V act_size $end
$var parameter 32 W kernel_size $end
$var reg 16 X data_out [15:0] $end
$var reg 16 Y east_data_o [15:0] $end
$var reg 1 ) east_enable_o $end
$var reg 1 Z load_ff0 $end
$var reg 1 [ load_ff1 $end
$var reg 1 \ load_spad_ctrl_c $end
$var reg 16 ] north_data_o [15:0] $end
$var reg 1 % north_enable_o $end
$var reg 16 ^ south_data_o [15:0] $end
$var reg 1 # south_enable_o $end
$var reg 16 _ west_data_o [15:0] $end
$var reg 1 ! west_enable_o $end
$scope module router_weight_0 $end
$var wire 1 . clk $end
$var wire 1 : load_spad_ctrl $end
$var wire 16 ` r_data_glb_wght [15:0] $end
$var wire 1 3 reset $end
$var parameter 32 a ADDR_BITWIDTH_GLB $end
$var parameter 32 b ADDR_BITWIDTH_SPAD $end
$var parameter 32 c DATA_BITWIDTH $end
$var parameter 3 d IDLE $end
$var parameter 3 e READ_GLB $end
$var parameter 32 f TOTAL_WEIGHTS $end
$var parameter 3 g WRITE_SPAD $end
$var parameter 32 h W_LOAD_ADDR $end
$var parameter 10 i W_READ_ADDR $end
$var parameter 32 j X_dim $end
$var parameter 32 k Y_dim $end
$var parameter 32 l act_size $end
$var parameter 32 m kernel_size $end
$var reg 6 n filt_count [5:0] $end
$var reg 1 ? load_en_spad $end
$var reg 10 o r_addr_glb_wght [9:0] $end
$var reg 1 ' read_req_glb_wght $end
$var reg 3 p state [2:0] $end
$var reg 16 q w_data_spad [15:0] $end
$upscope $end
$upscope $end
$upscope $end
$enddefinitions $end
$comment Show the parameter values. $end
$dumpall
b11 m
b101 l
b11 k
b101 j
b1000000 i
b0 h
b10 g
b1001 f
b1 e
b0 d
b10000 c
b1001 b
b1010 a
b11 W
b101 V
b11 U
b101 T
b1000000 S
b0 R
b1001 Q
b1000 P
b1010 O
b11 N
b10 M
b1 L
b111 K
b110 J
b101 I
b100 H
b10000 G
b10 F
b1011 E
b0 D
b1001 C
b1010 B
b10 -
b10000 ,
b1010 +
$end
#0
$dumpvars
b0 q
b0 p
b0 o
b0 n
b0 `
b0 _
b0 ^
b0 ]
0\
x[
xZ
b0 Y
b0 X
b0 A
b0 @
0?
b0 >
b0 =
b0 <
b0 ;
x:
b0 9
08
b0 7
06
b0 5
b0 4
13
02
b0 1
00
b0 /
0.
b0 *
0)
b0 (
0'
b0 &
0%
b0 $
0#
b0 "
0!
$end
#5000
0:
0[
0Z
1.
#10000
0.
#15000
1.
#20000
b1000100010001 $
b1000100010001 ^
1\
b1000100010001 X
b1000100010001 `
1#
0.
12
b1000100010001 1
b1000100010001 ;
b10 4
b10 <
03
#25000
1:
1Z
1.
#30000
b0 $
b0 ^
0\
b0 X
b0 `
0.
02
#35000
0:
b1 p
b1000000 (
b1000000 A
b1000000 o
1'
1[
0Z
1.
#40000
0.
#45000
b10 p
0[
1.
#50000
0.
#55000
1!
0#
b1 p
b1000001 (
b1000001 A
b1000001 o
b1 n
1?
1.
#60000
0.
#65000
0!
b10 p
0?
1.
#70000
b1010101010101010 &
b1010101010101010 ]
1\
b1010101010101010 X
b1010101010101010 `
1%
0.
10
b1010101010101010 /
b1010101010101010 9
b1 4
b1 <
#75000
1!
0%
b0 &
b0 ]
1:
b1 p
b1000010 (
b1000010 A
b1000010 o
b10 n
1?
1Z
1.
#80000
1%
0\
b0 X
b0 `
0.
00
#85000
0!
0%
0:
b10 p
0?
1[
0Z
1.
#90000
0.
#95000
1!
b1 p
b1000011 (
b1000011 A
b1000011 o
b11 n
1?
0[
1.
#100000
0.
#105000
0!
b10 p
0?
1.
#110000
0.
#115000
1!
b1 p
b1000100 (
b1000100 A
b1000100 o
b100 n
1?
1.
#120000
0.
#125000
0!
b10 p
0?
1.
#130000
0.
#135000
1!
b1 p
b1000101 (
b1000101 A
b1000101 o
b101 n
1?
1.
#140000
0.
#145000
0!
b10 p
0?
1.
#150000
0.
#155000
1!
b1 p
b1000110 (
b1000110 A
b1000110 o
b110 n
1?
1.
#160000
0.
#165000
0!
b10 p
0?
1.
#170000
0.
#175000
1!
b1 p
b1000111 (
b1000111 A
b1000111 o
b111 n
1?
1.
#180000
0.
#185000
0!
b10 p
0?
1.
#190000
0.
#195000
1!
b1 p
b1001000 (
b1001000 A
b1001000 o
b1000 n
1?
1.
#200000
1%
b101010101010101 &
b101010101010101 ]
1\
b101010101010101 X
b101010101010101 `
0.
10
b101010101010101 /
b101010101010101 9
#205000
b101010101010101 "
b101010101010101 _
0!
0%
b0 &
b0 ]
1:
b10 p
b101010101010101 @
b101010101010101 q
0?
1Z
1.
#210000
1%
0\
b0 X
b0 `
0.
00
#215000
1!
0%
b101010101010101 "
b101010101010101 _
0:
b0 p
b0 n
0'
1?
1[
0Z
1.
#220000
0.
#225000
0!
b101010101010101 "
b101010101010101 _
0?
0[
1.
