Generic_Routers/MAC.v
module MAC #(
    parameter IN_BITWIDTH = 16,
    parameter OUT_BITWIDTH = 16
)(
    input clk,
    input reset,
    input en,
    input [IN_BITWIDTH-1:0] a_in,
    input [IN_BITWIDTH-1:0] w_in,
    input [OUT_BITWIDTH-1:0] sum_in,
    output reg [OUT_BITWIDTH-1:0] out
);

always @(posedge clk) begin
    if (reset)
        out <= {OUT_BITWIDTH{1'b0}};
    else if (en)
        out <= (a_in * w_in) + sum_in;
end

endmodule

Generic_Routers/SPad.v
`timescale 1ns / 1ps

module SPad #(
    parameter DATA_BITWIDTH = 16,
    parameter ADDR_BITWIDTH = 9
)(
    input  clk,
    input  reset,
    input  read_req,
    input  write_en,
    input  [ADDR_BITWIDTH-1:0] r_addr,
    input  [ADDR_BITWIDTH-1:0] w_addr,
    input  [DATA_BITWIDTH-1:0] w_data,
    output reg [DATA_BITWIDTH-1:0] r_data
);

    // Memory array
    reg [DATA_BITWIDTH-1:0] mem [0:(1<<ADDR_BITWIDTH)-1];

    // ---------------- READ ----------------
    // Synchronous read
    always @(posedge clk) begin
        if (reset) begin
            r_data <= {DATA_BITWIDTH{1'b0}};
        end else if (read_req) begin
            r_data <= mem[r_addr];
        end else
        	r_data <= mem[r_addr];
        // else: HOLD last value (DO NOTHING)
    end

    // ---------------- WRITE ----------------
    always @(posedge clk) begin
        if (!reset && write_en) begin
            mem[w_addr] <= w_data;
        end
    end

endmodule

Generic_Routers/PE_new.v
`timescale 1ns / 1ps

module PE_new #(
    parameter DATA_BITWIDTH = 16,
    parameter ADDR_BITWIDTH = 9,

    parameter W_READ_ADDR  = 0,
    parameter A_READ_ADDR  = 100,
    parameter W_LOAD_ADDR  = 0,
    parameter A_LOAD_ADDR  = 100,

    parameter PSUM_ADDR    = 500,   // <<< ADDED

    parameter kernel_size  = 3,
    parameter act_size     = 5
)(
    input  clk,
    input  reset,

    input  [DATA_BITWIDTH-1:0] act_in,
    input  [DATA_BITWIDTH-1:0] filt_in,

    input  load_en_wght,
    input  load_en_act,
    input  start,

    output reg [DATA_BITWIDTH-1:0] pe_out,
    output reg compute_done,
    output reg load_done
);

    // ==================================================
    // FSM STATES
    // ==================================================
    localparam IDLE        = 5'd0,
               LD_W_ADDR   = 5'd1,
               LD_W_WRITE  = 5'd2,
               LD_A_ADDR   = 5'd3,
               LD_A_WRITE  = 5'd4,

               RD_W_ADDR   = 5'd5,
               RD_W_REQ    = 5'd6,
               RD_W_WAIT   = 5'd7,
               RD_W_LATCH  = 5'd8,

               RD_A_ADDR   = 5'd9,
               RD_A_REQ    = 5'd10,
               RD_A_WAIT   = 5'd11,
               RD_A_LATCH  = 5'd12,

               MAC_FIRE    = 5'd13,
               MAC_WAIT    = 5'd14,
               ACCUM       = 5'd15,
               COMMIT      = 5'd16;

    reg [4:0] state;

    // ==================================================
    // CONTROL
    // ==================================================
    reg busy;

    // ==================================================
    // SPAD INTERFACE
    // ==================================================
    reg read_en, write_en;
    reg [ADDR_BITWIDTH-1:0] r_addr, w_addr;
    reg [DATA_BITWIDTH-1:0] w_data;
    wire [DATA_BITWIDTH-1:0] r_data;

    SPad #(
        .DATA_BITWIDTH(DATA_BITWIDTH),
        .ADDR_BITWIDTH(ADDR_BITWIDTH)
    ) spad (
        .clk      (clk),
        .reset    (reset),
        .read_req (read_en),
        .write_en (write_en),
        .r_addr   (r_addr),
        .w_addr   (w_addr),
        .w_data   (w_data),
        .r_data   (r_data)
    );

    // ==================================================
    // REGISTERED READ DATA
    // ==================================================
    reg [DATA_BITWIDTH-1:0] r_data_q;
    always @(posedge clk)
        r_data_q <= reset ? {DATA_BITWIDTH{1'b0}} : r_data;

    // ==================================================
    // OPERANDS
    // ==================================================
    reg [DATA_BITWIDTH-1:0] act_reg, wgt_reg;

    // ==================================================
    // MAC
    // ==================================================
    reg mac_en;
    wire [DATA_BITWIDTH-1:0] psum;

    MAC #(
        .IN_BITWIDTH (DATA_BITWIDTH),
        .OUT_BITWIDTH(DATA_BITWIDTH)
    ) mac (
        .clk   (clk),
        .reset (reset),
        .en    (mac_en),
        .a_in  (act_reg),
        .w_in  (wgt_reg),
        .sum_in({DATA_BITWIDTH{1'b0}}),
        .out   (psum)
    );

    // ==================================================
    // REGISTER MAC OUTPUT
    // ==================================================
    reg [DATA_BITWIDTH-1:0] psum_q;
    always @(posedge clk)
        psum_q <= reset ? {DATA_BITWIDTH{1'b0}} : psum;

    // ==================================================
    // COUNTERS
    // ==================================================
    reg [7:0] load_count;
    reg [7:0] rd_idx;
    reg [7:0] acc_count;

    // ==================================================
    // FSM
    // ==================================================
    always @(posedge clk) begin
        if (reset) begin
            state        <= IDLE;
            load_count   <= 0;
            rd_idx       <= 0;
            acc_count    <= 0;
            pe_out       <= 0;
            busy         <= 0;

            read_en      <= 0;
            write_en     <= 0;
            mac_en       <= 0;

            compute_done <= 0;
            load_done    <= 0;
        end else begin
            read_en      <= 0;
            write_en     <= 0;
            mac_en       <= 0;
            compute_done <= 0;
            load_done    <= 0;

            case (state)

            IDLE: begin
                if (load_en_wght) begin
                    load_count <= 0;
                    state <= LD_W_ADDR;
                end else if (load_en_act) begin
                    load_count <= 0;
                    state <= LD_A_ADDR;
                end else if (start && !busy) begin
                    busy      <= 1;
                    rd_idx    <= 0;
                    acc_count <= 0;
                    pe_out    <= 0;
                    state <= RD_W_ADDR;
                end
            end

            LD_W_ADDR: begin
                w_addr <= W_LOAD_ADDR + load_count;
                w_data <= filt_in;
                state  <= LD_W_WRITE;
            end

            LD_W_WRITE: begin
                write_en <= 1;
                if (load_count == kernel_size*kernel_size) begin
                    load_done <= 1;
                    state <= IDLE;
                end else begin
                    load_count <= load_count + 1;
                    state <= LD_W_ADDR;
                end
            end

            LD_A_ADDR: begin
                w_addr <= A_LOAD_ADDR + load_count;
                w_data <= act_in;
                state  <= LD_A_WRITE;
            end

            LD_A_WRITE: begin
                write_en <= 1;
                if (load_count == act_size*act_size) begin
                    load_done <= 1;
                    state <= IDLE;
                end else begin
                    load_count <= load_count + 1;
                    state <= LD_A_ADDR;
                end
            end

            RD_W_ADDR: begin
                r_addr <= W_READ_ADDR + rd_idx;
                state <= RD_W_REQ;
            end

            RD_W_REQ: begin
                read_en <= 1;
                state <= RD_W_WAIT;
            end

            RD_W_WAIT: state <= RD_W_LATCH;

            RD_W_LATCH: begin
                wgt_reg <= r_data_q;
                state <= RD_A_ADDR;
            end

            RD_A_ADDR: begin
                r_addr <= A_READ_ADDR + rd_idx;
                state <= RD_A_REQ;
            end

            RD_A_REQ: begin
                read_en <= 1;
                state <= RD_A_WAIT;
            end

            RD_A_WAIT: state <= RD_A_LATCH;

            RD_A_LATCH: begin
                act_reg <= r_data_q;
                state <= MAC_FIRE;
            end

            MAC_FIRE: begin
                mac_en <= 1;
                state <= MAC_WAIT;
            end

            MAC_WAIT: state <= ACCUM;

            ACCUM: begin
                pe_out <= pe_out + psum_q;
                acc_count <= acc_count + 1;

                if (acc_count == kernel_size)
                    state <= COMMIT;
                else begin
                    rd_idx <= rd_idx + 1;
                    state <= RD_W_ADDR;
                end
            end

            // ==================================================
            // PSUM WRITE-BACK (ONLY ADDITION)
            // ==================================================
            COMMIT: begin
                w_addr       <= PSUM_ADDR;   // <<< WRITE BACK
                w_data       <= pe_out;
                write_en     <= 1;

                compute_done <= 1;
                busy <= 0;
                state <= IDLE;
            end

            endcase
        end
    end

endmodule

Generic_Routers/PE_tb.v
`timescale 1ns / 1ps

module PE_new_tb;

    // -------------------------------------------------
    // Parameters
    // -------------------------------------------------
    localparam DATA_BITWIDTH = 16;
    localparam ADDR_BITWIDTH = 9;

    localparam kernel_size = 3;
    localparam act_size    = 5;

    localparam W_READ_ADDR = 0;
    localparam A_READ_ADDR = 100;
    localparam W_LOAD_ADDR = 0;
    localparam A_LOAD_ADDR = 100;
    localparam PSUM_ADDR   = 500;

    // -------------------------------------------------
    // Signals
    // -------------------------------------------------
    reg clk;
    reg reset;

    reg  [DATA_BITWIDTH-1:0] act_in;
    reg  [DATA_BITWIDTH-1:0] filt_in;

    reg load_en_wght;
    reg load_en_act;
    reg start;

    wire [DATA_BITWIDTH-1:0] pe_out;
    wire compute_done;
    wire load_done;

    // -------------------------------------------------
    // DUT
    // -------------------------------------------------
    PE_new #(
        .DATA_BITWIDTH(DATA_BITWIDTH),
        .ADDR_BITWIDTH(ADDR_BITWIDTH),
        .kernel_size(kernel_size),
        .act_size(act_size),
        .W_READ_ADDR(W_READ_ADDR),
        .A_READ_ADDR(A_READ_ADDR),
        .W_LOAD_ADDR(W_LOAD_ADDR),
        .A_LOAD_ADDR(A_LOAD_ADDR),
        .PSUM_ADDR(PSUM_ADDR)
    ) dut (
        .clk(clk),
        .reset(reset),
        .act_in(act_in),
        .filt_in(filt_in),
        .load_en_wght(load_en_wght),
        .load_en_act(load_en_act),
        .start(start),
        .pe_out(pe_out),
        .compute_done(compute_done),
        .load_done(load_done)
    );

    // -------------------------------------------------
    // Clock
    // -------------------------------------------------
    always #5 clk = ~clk;

    // -------------------------------------------------
    // Test vectors
    // -------------------------------------------------
    reg [DATA_BITWIDTH-1:0] weights [0:kernel_size-1];
    reg [DATA_BITWIDTH-1:0] acts    [0:kernel_size-1];

    reg [DATA_BITWIDTH-1:0] expected_last_mac;
    reg [DATA_BITWIDTH-1:0] psum_mem;

    integer i;

    // -------------------------------------------------
    // Direct SPAD access (legal for TB)
    // -------------------------------------------------
    wire [DATA_BITWIDTH-1:0] spad_psum =
        dut.spad.mem[PSUM_ADDR];

    // -------------------------------------------------
    // Tasks
    // -------------------------------------------------
    task load_weights;
    begin
        $display("=== LOADING WEIGHTS ===");
        load_en_wght = 1;
        for (i = 0; i < kernel_size*kernel_size; i = i + 1) begin
            filt_in = weights[i % kernel_size];
            @(posedge clk);
        end
        load_en_wght = 0;
        filt_in = 0;

        wait (load_done);
        @(posedge clk);
        $display("[TB] Weight load complete");
    end
    endtask

    task load_activations;
    begin
        $display("=== LOADING ACTIVATIONS ===");
        load_en_act = 1;
        for (i = 0; i < act_size*act_size; i = i + 1) begin
            act_in = acts[i % kernel_size];
            @(posedge clk);
        end
        load_en_act = 0;
        act_in = 0;

        wait (load_done);
        @(posedge clk);
        $display("[TB] Activation load complete");
    end
    endtask

    // -------------------------------------------------
    // Test sequence
    // -------------------------------------------------
    initial begin
        $dumpfile("pe_new_tb.vcd");
        $dumpvars(0, PE_new_tb);

        // Init
        clk = 0;
        reset = 1;
        act_in = 0;
        filt_in = 0;
        load_en_wght = 0;
        load_en_act = 0;
        start = 0;

        // Define vectors
        weights[0] = 1;
        weights[1] = 2;
        weights[2] = 3;

        acts[0] = 1;
        acts[1] = 2;
        acts[2] = 3;

        // Modified PE produces ONLY last MAC
        expected_last_mac = acts[0]*weights[0] + acts[1]*weights[1] + acts[2]*weights[2];  // 3 * 3 = 9

        // Reset
        repeat (4) @(posedge clk);
        reset = 0;
        $display("=== RESET DEASSERTED ===");

        // Load
        load_weights();
        load_activations();

        // -------------------------------------------------
        // START COMPUTE
        // -------------------------------------------------
        $display("=== START COMPUTE ===");
        @(posedge clk);
        start = 1;
        @(posedge clk);
        start = 0;

        // Wait for compute_done
        wait (compute_done);
        $display("[TB] compute_done asserted");

        // Allow PSUM write-back to settle
        repeat (2) @(posedge clk);

        // -------------------------------------------------
        // CHECK RESULT
        // -------------------------------------------------
        psum_mem = spad_psum;

        $display("PE_OUT (last MAC) = %0d", pe_out);
        $display("PSUM_MEM         = %0d", psum_mem);
        $display("EXPECTED         = %0d", expected_last_mac);

        if (psum_mem !== expected_last_mac) begin
            $display("❌ FAIL: PSUM mismatch");
            $fatal;
        end else begin
            $display("✅ PASS: Modified PE verified");
        end

        #20;
        $finish;
    end

endmodule

Generic_Routers/pe_new_tb.vcd
$date
	Mon Dec 29 22:26:45 2025
$end
$version
	Icarus Verilog
$end
$timescale
	1ps
$end
$scope module PE_new_tb $end
$var wire 16 ! spad_psum [15:0] $end
$var wire 16 " pe_out [15:0] $end
$var wire 1 # load_done $end
$var wire 1 $ compute_done $end
$var parameter 32 % ADDR_BITWIDTH $end
$var parameter 32 & A_LOAD_ADDR $end
$var parameter 32 ' A_READ_ADDR $end
$var parameter 32 ( DATA_BITWIDTH $end
$var parameter 32 ) PSUM_ADDR $end
$var parameter 32 * W_LOAD_ADDR $end
$var parameter 32 + W_READ_ADDR $end
$var parameter 32 , act_size $end
$var parameter 32 - kernel_size $end
$var reg 16 . act_in [15:0] $end
$var reg 1 / clk $end
$var reg 16 0 expected_last_mac [15:0] $end
$var reg 16 1 filt_in [15:0] $end
$var reg 1 2 load_en_act $end
$var reg 1 3 load_en_wght $end
$var reg 16 4 psum_mem [15:0] $end
$var reg 1 5 reset $end
$var reg 1 6 start $end
$var integer 32 7 i [31:0] $end
$scope module dut $end
$var wire 16 8 act_in [15:0] $end
$var wire 1 / clk $end
$var wire 16 9 filt_in [15:0] $end
$var wire 1 2 load_en_act $end
$var wire 1 3 load_en_wght $end
$var wire 1 5 reset $end
$var wire 1 6 start $end
$var wire 16 : r_data [15:0] $end
$var wire 16 ; psum [15:0] $end
$var parameter 5 < ACCUM $end
$var parameter 32 = ADDR_BITWIDTH $end
$var parameter 32 > A_LOAD_ADDR $end
$var parameter 32 ? A_READ_ADDR $end
$var parameter 5 @ COMMIT $end
$var parameter 32 A DATA_BITWIDTH $end
$var parameter 5 B IDLE $end
$var parameter 5 C LD_A_ADDR $end
$var parameter 5 D LD_A_WRITE $end
$var parameter 5 E LD_W_ADDR $end
$var parameter 5 F LD_W_WRITE $end
$var parameter 5 G MAC_FIRE $end
$var parameter 5 H MAC_WAIT $end
$var parameter 32 I PSUM_ADDR $end
$var parameter 5 J RD_A_ADDR $end
$var parameter 5 K RD_A_LATCH $end
$var parameter 5 L RD_A_REQ $end
$var parameter 5 M RD_A_WAIT $end
$var parameter 5 N RD_W_ADDR $end
$var parameter 5 O RD_W_LATCH $end
$var parameter 5 P RD_W_REQ $end
$var parameter 5 Q RD_W_WAIT $end
$var parameter 32 R W_LOAD_ADDR $end
$var parameter 32 S W_READ_ADDR $end
$var parameter 32 T act_size $end
$var parameter 32 U kernel_size $end
$var reg 8 V acc_count [7:0] $end
$var reg 16 W act_reg [15:0] $end
$var reg 1 X busy $end
$var reg 1 $ compute_done $end
$var reg 8 Y load_count [7:0] $end
$var reg 1 # load_done $end
$var reg 1 Z mac_en $end
$var reg 16 [ pe_out [15:0] $end
$var reg 16 \ psum_q [15:0] $end
$var reg 9 ] r_addr [8:0] $end
$var reg 16 ^ r_data_q [15:0] $end
$var reg 8 _ rd_idx [7:0] $end
$var reg 1 ` read_en $end
$var reg 5 a state [4:0] $end
$var reg 9 b w_addr [8:0] $end
$var reg 16 c w_data [15:0] $end
$var reg 16 d wgt_reg [15:0] $end
$var reg 1 e write_en $end
$scope module mac $end
$var wire 16 f a_in [15:0] $end
$var wire 1 / clk $end
$var wire 1 Z en $end
$var wire 1 5 reset $end
$var wire 16 g sum_in [15:0] $end
$var wire 16 h w_in [15:0] $end
$var parameter 32 i IN_BITWIDTH $end
$var parameter 32 j OUT_BITWIDTH $end
$var reg 16 k out [15:0] $end
$upscope $end
$scope module spad $end
$var wire 1 / clk $end
$var wire 9 l r_addr [8:0] $end
$var wire 1 ` read_req $end
$var wire 1 5 reset $end
$var wire 9 m w_addr [8:0] $end
$var wire 16 n w_data [15:0] $end
$var wire 1 e write_en $end
$var parameter 32 o ADDR_BITWIDTH $end
$var parameter 32 p DATA_BITWIDTH $end
$var reg 16 q r_data [15:0] $end
$upscope $end
$upscope $end
$scope task load_activations $end
$upscope $end
$scope task load_weights $end
$upscope $end
$upscope $end
$enddefinitions $end
$comment Show the parameter values. $end
$dumpall
b10000 p
b1001 o
b10000 j
b10000 i
b11 U
b101 T
b0 S
b0 R
b111 Q
b110 P
b1000 O
b101 N
b1011 M
b1010 L
b1100 K
b1001 J
b111110100 I
b1110 H
b1101 G
b10 F
b1 E
b100 D
b11 C
b0 B
b10000 A
b10000 @
b1100100 ?
b1100100 >
b1001 =
b1111 <
b11 -
b101 ,
b0 +
b0 *
b111110100 )
b10000 (
b1100100 '
b1100100 &
b1001 %
$end
#0
$dumpvars
bx q
bx n
bx m
bx l
bx k
bx h
b0 g
bx f
xe
bx d
bx c
bx b
bx a
x`
bx _
bx ^
bx ]
bx \
bx [
xZ
bx Y
xX
bx W
bx V
bx ;
bx :
b0 9
b0 8
bx 7
06
15
bx 4
03
02
b0 1
b1110 0
0/
b0 .
x$
x#
bx "
bx !
$end
#5000
b0 :
b0 q
b0 ;
b0 k
b0 ^
b0 \
0#
0$
0Z
0e
0`
0X
b0 "
b0 [
b0 V
b0 _
b0 Y
b0 a
1/
#10000
0/
#15000
1/
#20000
0/
#25000
1/
#30000
0/
#35000
b1 1
b1 9
b0 7
13
05
1/
#40000
0/
#45000
bx :
bx q
b1 a
b10 1
b10 9
b1 7
1/
#50000
0/
#55000
b10 a
b10 c
b10 n
b0 b
b0 m
bx ^
b11 1
b11 9
b10 7
1/
#60000
0/
#65000
b1 a
b1 Y
1e
b1 1
b1 9
b11 7
1/
#70000
0/
#75000
b10 a
b1 c
b1 n
b1 b
b1 m
0e
b10 1
b10 9
b100 7
1/
#80000
0/
#85000
b1 a
b10 Y
1e
b11 1
b11 9
b101 7
1/
#90000
0/
#95000
b10 a
b11 c
b11 n
b10 b
b10 m
0e
b1 1
b1 9
b110 7
1/
#100000
0/
#105000
b1 a
b11 Y
1e
b10 1
b10 9
b111 7
1/
#110000
0/
#115000
b10 a
b10 c
b10 n
b11 b
b11 m
0e
b11 1
b11 9
b1000 7
1/
#120000
0/
#125000
b1 a
b100 Y
1e
b0 1
b0 9
03
b1001 7
1/
#130000
0/
#135000
b10 a
b0 c
b0 n
b100 b
b100 m
0e
1/
#140000
0/
#145000
b1 a
b101 Y
1e
1/
#150000
0/
#155000
b10 a
b101 b
b101 m
0e
1/
#160000
0/
#165000
b1 a
b110 Y
1e
1/
#170000
0/
#175000
b10 a
b110 b
b110 m
0e
1/
#180000
0/
#185000
b1 a
b111 Y
1e
1/
#190000
0/
#195000
b10 a
b111 b
b111 m
0e
1/
#200000
0/
#205000
b1 a
b1000 Y
1e
1/
#210000
0/
#215000
b10 a
b1000 b
b1000 m
0e
1/
#220000
0/
#225000
b1 a
b1001 Y
1e
1/
#230000
0/
#235000
b10 a
b1001 b
b1001 m
0e
1/
#240000
0/
#245000
b0 a
1#
1e
1/
#250000
0/
#255000
0#
0e
b1 .
b1 8
b0 7
12
1/
#260000
0/
#265000
b11 a
b0 Y
b10 .
b10 8
b1 7
1/
#270000
0/
#275000
b100 a
b10 c
b10 n
b1100100 b
b1100100 m
b11 .
b11 8
b10 7
1/
#280000
0/
#285000
b11 a
b1 Y
1e
b1 .
b1 8
b11 7
1/
#290000
0/
#295000
b100 a
b1 c
b1 n
b1100101 b
b1100101 m
0e
b10 .
b10 8
b100 7
1/
#300000
0/
#305000
b11 a
b10 Y
1e
b11 .
b11 8
b101 7
1/
#310000
0/
#315000
b100 a
b11 c
b11 n
b1100110 b
b1100110 m
0e
b1 .
b1 8
b110 7
1/
#320000
0/
#325000
b11 a
b11 Y
1e
b10 .
b10 8
b111 7
1/
#330000
0/
#335000
b100 a
b10 c
b10 n
b1100111 b
b1100111 m
0e
b11 .
b11 8
b1000 7
1/
#340000
0/
#345000
b11 a
b100 Y
1e
b1 .
b1 8
b1001 7
1/
#350000
0/
#355000
b100 a
b1 c
b1 n
b1101000 b
b1101000 m
0e
b10 .
b10 8
b1010 7
1/
#360000
0/
#365000
b11 a
b101 Y
1e
b11 .
b11 8
b1011 7
1/
#370000
0/
#375000
b100 a
b11 c
b11 n
b1101001 b
b1101001 m
0e
b1 .
b1 8
b1100 7
1/
#380000
0/
#385000
b11 a
b110 Y
1e
b10 .
b10 8
b1101 7
1/
#390000
0/
#395000
b100 a
b10 c
b10 n
b1101010 b
b1101010 m
0e
b11 .
b11 8
b1110 7
1/
#400000
0/
#405000
b11 a
b111 Y
1e
b1 .
b1 8
b1111 7
1/
#410000
0/
#415000
b100 a
b1 c
b1 n
b1101011 b
b1101011 m
0e
b10 .
b10 8
b10000 7
1/
#420000
0/
#425000
b11 a
b1000 Y
1e
b11 .
b11 8
b10001 7
1/
#430000
0/
#435000
b100 a
b11 c
b11 n
b1101100 b
b1101100 m
0e
b1 .
b1 8
b10010 7
1/
#440000
0/
#445000
b11 a
b1001 Y
1e
b10 .
b10 8
b10011 7
1/
#450000
0/
#455000
b100 a
b10 c
b10 n
b1101101 b
b1101101 m
0e
b11 .
b11 8
b10100 7
1/
#460000
0/
#465000
b11 a
b1010 Y
1e
b1 .
b1 8
b10101 7
1/
#470000
0/
#475000
b100 a
b1 c
b1 n
b1101110 b
b1101110 m
0e
b10 .
b10 8
b10110 7
1/
#480000
0/
#485000
b11 a
b1011 Y
1e
b11 .
b11 8
b10111 7
1/
#490000
0/
#495000
b100 a
b11 c
b11 n
b1101111 b
b1101111 m
0e
b1 .
b1 8
b11000 7
1/
#500000
0/
#505000
b11 a
b1100 Y
1e
b0 .
b0 8
02
b11001 7
1/
#510000
0/
#515000
b100 a
b0 c
b0 n
b1110000 b
b1110000 m
0e
1/
#520000
0/
#525000
b11 a
b1101 Y
1e
1/
#530000
0/
#535000
b100 a
b1110001 b
b1110001 m
0e
1/
#540000
0/
#545000
b11 a
b1110 Y
1e
1/
#550000
0/
#555000
b100 a
b1110010 b
b1110010 m
0e
1/
#560000
0/
#565000
b11 a
b1111 Y
1e
1/
#570000
0/
#575000
b100 a
b1110011 b
b1110011 m
0e
1/
#580000
0/
#585000
b11 a
b10000 Y
1e
1/
#590000
0/
#595000
b100 a
b1110100 b
b1110100 m
0e
1/
#600000
0/
#605000
b11 a
b10001 Y
1e
1/
#610000
0/
#615000
b100 a
b1110101 b
b1110101 m
0e
1/
#620000
0/
#625000
b11 a
b10010 Y
1e
1/
#630000
0/
#635000
b100 a
b1110110 b
b1110110 m
0e
1/
#640000
0/
#645000
b11 a
b10011 Y
1e
1/
#650000
0/
#655000
b100 a
b1110111 b
b1110111 m
0e
1/
#660000
0/
#665000
b11 a
b10100 Y
1e
1/
#670000
0/
#675000
b100 a
b1111000 b
b1111000 m
0e
1/
#680000
0/
#685000
b11 a
b10101 Y
1e
1/
#690000
0/
#695000
b100 a
b1111001 b
b1111001 m
0e
1/
#700000
0/
#705000
b11 a
b10110 Y
1e
1/
#710000
0/
#715000
b100 a
b1111010 b
b1111010 m
0e
1/
#720000
0/
#725000
b11 a
b10111 Y
1e
1/
#730000
0/
#735000
b100 a
b1111011 b
b1111011 m
0e
1/
#740000
0/
#745000
b11 a
b11000 Y
1e
1/
#750000
0/
#755000
b100 a
b1111100 b
b1111100 m
0e
1/
#760000
0/
#765000
b11 a
b11001 Y
1e
1/
#770000
0/
#775000
b100 a
b1111101 b
b1111101 m
0e
1/
#780000
0/
#785000
b0 a
1#
1e
1/
#790000
0/
#795000
0#
0e
1/
#800000
0/
#805000
b101 a
1X
16
1/
#810000
0/
#815000
b110 a
b0 ]
b0 l
06
1/
#820000
0/
#825000
b10 :
b10 q
b111 a
1`
1/
#830000
0/
#835000
b1000 a
0`
b10 ^
1/
#840000
0/
#845000
b1001 a
b10 d
b10 h
1/
#850000
0/
#855000
b1010 a
b1100100 ]
b1100100 l
1/
#860000
0/
#865000
b1011 a
1`
1/
#870000
0/
#875000
b1100 a
0`
1/
#880000
0/
#885000
b1101 a
b10 W
b10 f
1/
#890000
0/
#895000
b1110 a
1Z
1/
#900000
0/
#905000
b100 ;
b100 k
b1111 a
0Z
1/
#910000
0/
#915000
b101 a
b1 _
b1 V
b100 \
1/
#920000
0/
#925000
b110 a
b1 ]
b1 l
1/
#930000
0/
#935000
b111 a
1`
b1 :
b1 q
1/
#940000
0/
#945000
b1 ^
b1000 a
0`
1/
#950000
0/
#955000
b1001 a
b1 d
b1 h
1/
#960000
0/
#965000
b1010 a
b1100101 ]
b1100101 l
1/
#970000
0/
#975000
b1011 a
1`
1/
#980000
0/
#985000
b1100 a
0`
1/
#990000
0/
#995000
b1101 a
b1 W
b1 f
1/
#1000000
0/
#1005000
b1110 a
1Z
1/
#1010000
0/
#1015000
b1111 a
0Z
b1 ;
b1 k
1/
#1020000
0/
#1025000
b1 \
b101 a
b10 _
b10 V
b100 "
b100 [
1/
#1030000
0/
#1035000
b110 a
b10 ]
b10 l
1/
#1040000
0/
#1045000
b11 :
b11 q
b111 a
1`
1/
#1050000
0/
#1055000
b1000 a
0`
b11 ^
1/
#1060000
0/
#1065000
b1001 a
b11 d
b11 h
1/
#1070000
0/
#1075000
b1010 a
b1100110 ]
b1100110 l
1/
#1080000
0/
#1085000
b1011 a
1`
1/
#1090000
0/
#1095000
b1100 a
0`
1/
#1100000
0/
#1105000
b1101 a
b11 W
b11 f
1/
#1110000
0/
#1115000
b1110 a
1Z
1/
#1120000
0/
#1125000
b1001 ;
b1001 k
b1111 a
0Z
1/
#1130000
0/
#1135000
b101 a
b11 _
b11 V
b101 "
b101 [
b1001 \
1/
#1140000
0/
#1145000
b110 a
b11 ]
b11 l
1/
#1150000
0/
#1155000
b111 a
1`
b10 :
b10 q
1/
#1160000
0/
#1165000
b10 ^
b1000 a
0`
1/
#1170000
0/
#1175000
b1001 a
b10 d
b10 h
1/
#1180000
0/
#1185000
b1010 a
b1100111 ]
b1100111 l
1/
#1190000
0/
#1195000
b1011 a
1`
1/
#1200000
0/
#1205000
b1100 a
0`
1/
#1210000
0/
#1215000
b1101 a
b10 W
b10 f
1/
#1220000
0/
#1225000
b1110 a
1Z
1/
#1230000
0/
#1235000
b1111 a
0Z
b100 ;
b100 k
1/
#1240000
0/
#1245000
b100 \
b10000 a
b100 V
b1110 "
b1110 [
1/
#1250000
0/
#1255000
b0 a
0X
1$
1e
b1110 c
b1110 n
b111110100 b
b111110100 m
1/
#1260000
0/
#1265000
b1110 !
0$
0e
1/
#1270000
0/
#1275000
b1110 4
1/
